[
  {
    "serial": 0,
    "orderId": null,
    "positionId": 1,
    "event": "Create Position",
    "time": 1782812700049,
    "volume": 1,
    "quantity": 0.01,
    "type": "Buy",
    "entryPrice": 4018.77,
    "tp": 4111.42,
    "sl": 3972.1,
    "closePrice": null,
    "grossProfit": 0,
    "pips": 0,
    "balance": null,
    "equity": 10000
  },
  {
    "serial": 1,
    "orderId": null,
    "positionId": 1,
    "event": "Stop Loss Hit",
    "time": 1782871526772,
    "volume": 1,
    "quantity": 0.01,
    "type": "Buy",
    "entryPrice": 4018.77,
    "tp": 4111.42,
    "sl": 3972.1,
    "closePrice": 3971.85,
    "grossProfit": -46.92,
    "pips": -4692,
    "balance": 9952.31,
    "equity": 9951.779999999999
  },
  {
    "serial": 2,
    "orderId": null,
    "positionId": 2,
    "event": "Create Position",
    "time": 1782932400079,
    "volume": 6,
    "quantity": 0.06,
    "type": "Buy",
    "entryPrice": 4062.36,
    "tp": 4077.9900000000002,
    "sl": 4054.3900000000003,
    "closePrice": null,
    "grossProfit": 0,
    "pips": 0,
    "balance": null,
    "equity": 9952.31
  },
  {
    "serial": 3,
    "orderId": null,
    "positionId": 2,
    "event": "Stop Loss Hit",
    "time": 1782934925645,
    "volume": 6,
    "quantity": 0.06,
    "type": "Buy",
    "entryPrice": 4062.36,
    "tp": 4077.9900000000002,
    "sl": 4054.3900000000003,
    "closePrice": 4054.33,
    "grossProfit": -48.18,
    "pips": -802.9999999999999,
    "balance": 9902.689999999999,
    "equity": 9902.689999999999
  },
  {
    "serial": 4,
    "orderId": null,
    "positionId": 3,
    "event": "Create Position",
    "time": 1783070100141,
    "volume": 3,
    "quantity": 0.03,
    "type": "Buy",
    "entryPrice": 4180.54,
    "tp": 4207.04,
    "sl": 4167.17,
    "closePrice": null,
    "grossProfit": 0,
    "pips": 0,
    "balance": null,
    "equity": 9902.689999999999
  },
  {
    "serial": 5,
    "orderId": null,
    "positionId": 3,
    "event": "Stop Loss Hit",
    "time": 1783084169658,
    "volume": 3,
    "quantity": 0.03,
    "type": "Buy",
    "entryPrice": 4180.54,
    "tp": 4207.04,
    "sl": 4167.17,
    "closePrice": 4167.14,
    "grossProfit": -40.2,
    "pips": -1340,
    "balance": 9861.769999999999,
    "equity": 9861.769999999999
  },
  {
    "serial": 6,
    "orderId": null,
    "positionId": 4,
    "event": "Create Position",
    "time": 1783669500030,
    "volume": 3,
    "quantity": 0.03,
    "type": "Sell",
    "entryPrice": 4106.79,
    "tp": 4076.17,
    "sl": 4121.74,
    "closePrice": null,
    "grossProfit": 0,
    "pips": 0,
    "balance": null,
    "equity": 9861.769999999999
  },
  {
    "serial": 7,
    "orderId": null,
    "positionId": 4,
    "event": "Position Modified (S/L)",
    "time": 1783690065674,
    "volume": 3,
    "quantity": 0.03,
    "type": "Sell",
    "entryPrice": 4106.79,
    "tp": 4076.17,
    "sl": 4091.11,
    "closePrice": null,
    "grossProfit": 0,
    "pips": 0,
    "balance": null,
    "equity": 9912.56
  },
  {
    "serial": 8,
    "orderId": null,
    "positionId": 4,
    "event": "Position Modified (S/L)",
    "time": 1783690072975,
    "volume": 3,
    "quantity": 0.03,
    "type": "Sell",
    "entryPrice": 4106.79,
    "tp": 4076.17,
    "sl": 4091.09,
    "closePrice": null,
    "grossProfit": 0,
    "pips": 0,
    "balance": null,
    "equity": 9912.619999999999
  },
  {
    "serial": 9,
    "orderId": null,
    "positionId": 4,
    "event": "Position Modified (S/L)",
    "time": 1783690074410,
    "volume": 3,
    "quantity": 0.03,
    "type": "Sell",
    "entryPrice": 4106.79,
    "tp": 4076.17,
    "sl": 4091.06,
    "closePrice": null,
    "grossProfit": 0,
    "pips": 0,
    "balance": null,
    "equity": 9912.71
  },
  {
    "serial": 10,
    "orderId": null,
    "positionId": 4,
    "event": "Position Modified (S/L)",
    "time": 1783690075865,
    "volume": 3,
    "quantity": 0.03,
    "type": "Sell",
    "entryPrice": 4106.79,
    "tp": 4076.17,
    "sl": 4090.63,
    "closePrice": null,
    "grossProfit": 0,
    "pips": 0,
    "balance": null,
    "equity": 9913.999999999998
  },
  {
    "serial": 11,
    "orderId": null,
    "positionId": 4,
    "event": "Position Modified (S/L)",
    "time": 1783690076231,
    "volume": 3,
    "quantity": 0.03,
    "type": "Sell",
    "entryPrice": 4106.79,
    "tp": 4076.17,
    "sl": 4090.52,
    "closePrice": null,
    "grossProfit": 0,
    "pips": 0,
    "balance": null,
    "equity": 9914.329999999998
  },
  {
    "serial": 12,
    "orderId": null,
    "positionId": 4,
    "event": "Position Modified (S/L)",
    "time": 1783690079808,
    "volume": 3,
    "quantity": 0.03,
    "type": "Sell",
    "entryPrice": 4106.79,
    "tp": 4076.17,
    "sl": 4090.47,
    "closePrice": null,
    "grossProfit": 0,
    "pips": 0,
    "balance": null,
    "equity": 9914.479999999998
  },
  {
    "serial": 13,
    "orderId": null,
    "positionId": 4,
    "event": "Position Modified (S/L)",
    "time": 1783690080533,
    "volume": 3,
    "quantity": 0.03,
    "type": "Sell",
    "entryPrice": 4106.79,
    "tp": 4076.17,
    "sl": 4090.32,
    "closePrice": null,
    "grossProfit": 0,
    "pips": 0,
    "balance": null,
    "equity": 9914.929999999998
  },
  {
    "serial": 14,
    "orderId": null,
    "positionId": 4,
    "event": "Position Modified (S/L)",
    "time": 1783690091340,
    "volume": 3,
    "quantity": 0.03,
    "type": "Sell",
    "entryPrice": 4106.79,
    "tp": 4076.17,
    "sl": 4090.13,
    "closePrice": null,
    "grossProfit": 0,
    "pips": 0,
    "balance": null,
    "equity": 9915.499999999998
  },
  {
    "serial": 15,
    "orderId": null,
    "positionId": 4,
    "event": "Position Modified (S/L)",
    "time": 1783690091705,
    "volume": 3,
    "quantity": 0.03,
    "type": "Sell",
    "entryPrice": 4106.79,
    "tp": 4076.17,
    "sl": 4090.11,
    "closePrice": null,
    "grossProfit": 0,
    "pips": 0,
    "balance": null,
    "equity": 9915.56
  },
  {
    "serial": 16,
    "orderId": null,
    "positionId": 4,
    "event": "Position Modified (S/L)",
    "time": 1783690092791,
    "volume": 3,
    "quantity": 0.03,
    "type": "Sell",
    "entryPrice": 4106.79,
    "tp": 4076.17,
    "sl": 4090.06,
    "closePrice": null,
    "grossProfit": 0,
    "pips": 0,
    "balance": null,
    "equity": 9915.71
  },
  {
    "serial": 17,
    "orderId": null,
    "positionId": 4,
    "event": "Position Modified (S/L)",
    "time": 1783690095696,
    "volume": 3,
    "quantity": 0.03,
    "type": "Sell",
    "entryPrice": 4106.79,
    "tp": 4076.17,
    "sl": 4090.02,
    "closePrice": null,
    "grossProfit": 0,
    "pips": 0,
    "balance": null,
    "equity": 9915.829999999998
  },
  {
    "serial": 18,
    "orderId": null,
    "positionId": 4,
    "event": "Position Modified (S/L)",
    "time": 1783690096048,
    "volume": 3,
    "quantity": 0.03,
    "type": "Sell",
    "entryPrice": 4106.79,
    "tp": 4076.17,
    "sl": 4089.77,
    "closePrice": null,
    "grossProfit": 0,
    "pips": 0,
    "balance": null,
    "equity": 9916.579999999998
  },
  {
    "serial": 19,
    "orderId": null,
    "positionId": 4,
    "event": "Stop Loss Hit",
    "time": 1783690101176,
    "volume": 3,
    "quantity": 0.03,
    "type": "Sell",
    "entryPrice": 4106.79,
    "tp": 4076.17,
    "sl": 4089.77,
    "closePrice": 4089.81,
    "grossProfit": 50.94,
    "pips": 1698,
    "balance": 9911.989999999998,
    "equity": 9911.989999999998
  },
  {
    "serial": 20,
    "orderId": null,
    "positionId": 5,
    "event": "Create Position",
    "time": 1784189700254,
    "volume": 4,
    "quantity": 0.04,
    "type": "Sell",
    "entryPrice": 4025.78,
    "tp": 4005.67,
    "sl": 4035.9,
    "closePrice": null,
    "grossProfit": 0,
    "pips": 0,
    "balance": null,
    "equity": 9911.989999999998
  },
  {
    "serial": 21,
    "orderId": null,
    "positionId": 5,
    "event": "Stop Loss Hit",
    "time": 1784191650341,
    "volume": 4,
    "quantity": 0.04,
    "type": "Sell",
    "entryPrice": 4025.78,
    "tp": 4005.67,
    "sl": 4035.9,
    "closePrice": 4036.07,
    "grossProfit": -41.16,
    "pips": -1029,
    "balance": 9869.869999999997,
    "equity": 9869.869999999997
  }
]