[
  {
    "serial": 0,
    "orderId": null,
    "positionId": 1,
    "event": "Create Position",
    "time": 1782080100243,
    "volume": 4,
    "quantity": 0.04,
    "type": "Sell",
    "entryPrice": 4151.57,
    "tp": 4131.2,
    "sl": 4161.8099999999995,
    "closePrice": null,
    "grossProfit": 0,
    "pips": 0,
    "balance": null,
    "equity": 10000
  },
  {
    "serial": 1,
    "orderId": null,
    "positionId": 1,
    "event": "Stop Loss Hit",
    "time": 1782083285965,
    "volume": 4,
    "quantity": 0.04,
    "type": "Sell",
    "entryPrice": 4151.57,
    "tp": 4131.2,
    "sl": 4161.8099999999995,
    "closePrice": 4161.84,
    "grossProfit": -41.08,
    "pips": -1027,
    "balance": 9957.96,
    "equity": 9957.96
  },
  {
    "serial": 2,
    "orderId": null,
    "positionId": 2,
    "event": "Create Position",
    "time": 1782315000354,
    "volume": 2,
    "quantity": 0.02,
    "type": "Buy",
    "entryPrice": 4015.32,
    "tp": 4063.02,
    "sl": 3990.78,
    "closePrice": null,
    "grossProfit": 0,
    "pips": 0,
    "balance": null,
    "equity": 9957.96
  },
  {
    "serial": 3,
    "orderId": null,
    "positionId": 2,
    "event": "Stop Loss Hit",
    "time": 1782321910351,
    "volume": 2,
    "quantity": 0.02,
    "type": "Buy",
    "entryPrice": 4015.32,
    "tp": 4063.02,
    "sl": 3990.78,
    "closePrice": 3990.66,
    "grossProfit": -49.32,
    "pips": -2466,
    "balance": 9908.16,
    "equity": 9908.16
  },
  {
    "serial": 4,
    "orderId": null,
    "positionId": 3,
    "event": "Create Position",
    "time": 1782367200336,
    "volume": 4,
    "quantity": 0.04,
    "type": "Buy",
    "entryPrice": 3986.24,
    "tp": 4009.97,
    "sl": 3974.75,
    "closePrice": null,
    "grossProfit": 0,
    "pips": 0,
    "balance": null,
    "equity": 9908.16
  },
  {
    "serial": 5,
    "orderId": null,
    "positionId": 3,
    "event": "Stop Loss Hit",
    "time": 1782368400166,
    "volume": 4,
    "quantity": 0.04,
    "type": "Buy",
    "entryPrice": 3986.24,
    "tp": 4009.97,
    "sl": 3974.75,
    "closePrice": 3974.7,
    "grossProfit": -46.16,
    "pips": -1154,
    "balance": 9861.039999999999,
    "equity": 9861.039999999999
  },
  {
    "serial": 6,
    "orderId": null,
    "positionId": 4,
    "event": "Create Position",
    "time": 1782417600270,
    "volume": 6,
    "quantity": 0.06,
    "type": "Buy",
    "entryPrice": 4027.04,
    "tp": 4041.91,
    "sl": 4019.13,
    "closePrice": null,
    "grossProfit": 0,
    "pips": 0,
    "balance": null,
    "equity": 9861.039999999999
  },
  {
    "serial": 7,
    "orderId": null,
    "positionId": 4,
    "event": "Position Modified (S/L)",
    "time": 1782427047786,
    "volume": 6,
    "quantity": 0.06,
    "type": "Buy",
    "entryPrice": 4027.04,
    "tp": 4041.91,
    "sl": 4034.68,
    "closePrice": null,
    "grossProfit": 0,
    "pips": 0,
    "balance": null,
    "equity": 9911.74
  },
  {
    "serial": 8,
    "orderId": null,
    "positionId": 4,
    "event": "Position Modified (S/L)",
    "time": 1782427048142,
    "volume": 6,
    "quantity": 0.06,
    "type": "Buy",
    "entryPrice": 4027.04,
    "tp": 4041.91,
    "sl": 4034.71,
    "closePrice": null,
    "grossProfit": 0,
    "pips": 0,
    "balance": null,
    "equity": 9911.919999999998
  },
  {
    "serial": 9,
    "orderId": null,
    "positionId": 4,
    "event": "Position Modified (S/L)",
    "time": 1782427048495,
    "volume": 6,
    "quantity": 0.06,
    "type": "Buy",
    "entryPrice": 4027.04,
    "tp": 4041.91,
    "sl": 4034.8,
    "closePrice": null,
    "grossProfit": 0,
    "pips": 0,
    "balance": null,
    "equity": 9912.46
  },
  {
    "serial": 10,
    "orderId": null,
    "positionId": 4,
    "event": "Stop Loss Hit",
    "time": 1782427076556,
    "volume": 6,
    "quantity": 0.06,
    "type": "Buy",
    "entryPrice": 4027.04,
    "tp": 4041.91,
    "sl": 4034.8,
    "closePrice": 4034.65,
    "grossProfit": 45.66,
    "pips": 761,
    "balance": 9902.08,
    "equity": 9898.9
  },
  {
    "serial": 11,
    "orderId": null,
    "positionId": 5,
    "event": "Create Position",
    "time": 1782701100263,
    "volume": 4,
    "quantity": 0.04,
    "type": "Buy",
    "entryPrice": 4060.74,
    "tp": 4082.2,
    "sl": 4049.58,
    "closePrice": null,
    "grossProfit": 0,
    "pips": 0,
    "balance": null,
    "equity": 9902.08
  },
  {
    "serial": 12,
    "orderId": null,
    "positionId": 5,
    "event": "Position Modified (S/L)",
    "time": 1782703263294,
    "volume": 4,
    "quantity": 0.04,
    "type": "Buy",
    "entryPrice": 4060.74,
    "tp": 4082.2,
    "sl": 4070.94,
    "closePrice": null,
    "grossProfit": 0,
    "pips": 0,
    "balance": null,
    "equity": 9950.84
  },
  {
    "serial": 13,
    "orderId": null,
    "positionId": 5,
    "event": "Position Modified (S/L)",
    "time": 1782703263645,
    "volume": 4,
    "quantity": 0.04,
    "type": "Buy",
    "entryPrice": 4060.74,
    "tp": 4082.2,
    "sl": 4070.98,
    "closePrice": null,
    "grossProfit": 0,
    "pips": 0,
    "balance": null,
    "equity": 9951
  },
  {
    "serial": 14,
    "orderId": null,
    "positionId": 5,
    "event": "Position Modified (S/L)",
    "time": 1782703264377,
    "volume": 4,
    "quantity": 0.04,
    "type": "Buy",
    "entryPrice": 4060.74,
    "tp": 4082.2,
    "sl": 4071.03,
    "closePrice": null,
    "grossProfit": 0,
    "pips": 0,
    "balance": null,
    "equity": 9951.2
  },
  {
    "serial": 15,
    "orderId": null,
    "positionId": 5,
    "event": "Position Modified (S/L)",
    "time": 1782703332548,
    "volume": 4,
    "quantity": 0.04,
    "type": "Buy",
    "entryPrice": 4060.74,
    "tp": 4082.2,
    "sl": 4071.05,
    "closePrice": null,
    "grossProfit": 0,
    "pips": 0,
    "balance": null,
    "equity": 9951.28
  },
  {
    "serial": 16,
    "orderId": null,
    "positionId": 5,
    "event": "Position Modified (S/L)",
    "time": 1782703334375,
    "volume": 4,
    "quantity": 0.04,
    "type": "Buy",
    "entryPrice": 4060.74,
    "tp": 4082.2,
    "sl": 4071.07,
    "closePrice": null,
    "grossProfit": 0,
    "pips": 0,
    "balance": null,
    "equity": 9951.36
  },
  {
    "serial": 17,
    "orderId": null,
    "positionId": 5,
    "event": "Position Modified (S/L)",
    "time": 1782703334738,
    "volume": 4,
    "quantity": 0.04,
    "type": "Buy",
    "entryPrice": 4060.74,
    "tp": 4082.2,
    "sl": 4071.13,
    "closePrice": null,
    "grossProfit": 0,
    "pips": 0,
    "balance": null,
    "equity": 9951.6
  },
  {
    "serial": 18,
    "orderId": null,
    "positionId": 5,
    "event": "Position Modified (S/L)",
    "time": 1782703335120,
    "volume": 4,
    "quantity": 0.04,
    "type": "Buy",
    "entryPrice": 4060.74,
    "tp": 4082.2,
    "sl": 4071.16,
    "closePrice": null,
    "grossProfit": 0,
    "pips": 0,
    "balance": null,
    "equity": 9951.72
  },
  {
    "serial": 19,
    "orderId": null,
    "positionId": 5,
    "event": "Position Modified (S/L)",
    "time": 1782703335478,
    "volume": 4,
    "quantity": 0.04,
    "type": "Buy",
    "entryPrice": 4060.74,
    "tp": 4082.2,
    "sl": 4071.32,
    "closePrice": null,
    "grossProfit": 0,
    "pips": 0,
    "balance": null,
    "equity": 9952.36
  },
  {
    "serial": 20,
    "orderId": null,
    "positionId": 5,
    "event": "Position Modified (S/L)",
    "time": 1782703342477,
    "volume": 4,
    "quantity": 0.04,
    "type": "Buy",
    "entryPrice": 4060.74,
    "tp": 4082.2,
    "sl": 4071.52,
    "closePrice": null,
    "grossProfit": 0,
    "pips": 0,
    "balance": null,
    "equity": 9953.16
  },
  {
    "serial": 21,
    "orderId": null,
    "positionId": 5,
    "event": "Position Modified (S/L)",
    "time": 1782703342866,
    "volume": 4,
    "quantity": 0.04,
    "type": "Buy",
    "entryPrice": 4060.74,
    "tp": 4082.2,
    "sl": 4071.92,
    "closePrice": null,
    "grossProfit": 0,
    "pips": 0,
    "balance": null,
    "equity": 9954.76
  },
  {
    "serial": 22,
    "orderId": null,
    "positionId": 5,
    "event": "Position Modified (S/L)",
    "time": 1782703343245,
    "volume": 4,
    "quantity": 0.04,
    "type": "Buy",
    "entryPrice": 4060.74,
    "tp": 4082.2,
    "sl": 4072.21,
    "closePrice": null,
    "grossProfit": 0,
    "pips": 0,
    "balance": null,
    "equity": 9955.92
  },
  {
    "serial": 23,
    "orderId": null,
    "positionId": 5,
    "event": "Position Modified (S/L)",
    "time": 1782703343615,
    "volume": 4,
    "quantity": 0.04,
    "type": "Buy",
    "entryPrice": 4060.74,
    "tp": 4082.2,
    "sl": 4072.36,
    "closePrice": null,
    "grossProfit": 0,
    "pips": 0,
    "balance": null,
    "equity": 9956.52
  },
  {
    "serial": 24,
    "orderId": null,
    "positionId": 5,
    "event": "Position Modified (S/L)",
    "time": 1782703343969,
    "volume": 4,
    "quantity": 0.04,
    "type": "Buy",
    "entryPrice": 4060.74,
    "tp": 4082.2,
    "sl": 4072.94,
    "closePrice": null,
    "grossProfit": 0,
    "pips": 0,
    "balance": null,
    "equity": 9958.84
  },
  {
    "serial": 25,
    "orderId": null,
    "positionId": 5,
    "event": "Position Modified (S/L)",
    "time": 1782703344705,
    "volume": 4,
    "quantity": 0.04,
    "type": "Buy",
    "entryPrice": 4060.74,
    "tp": 4082.2,
    "sl": 4073.27,
    "closePrice": null,
    "grossProfit": 0,
    "pips": 0,
    "balance": null,
    "equity": 9960.16
  },
  {
    "serial": 26,
    "orderId": null,
    "positionId": 5,
    "event": "Position Modified (S/L)",
    "time": 1782703349497,
    "volume": 4,
    "quantity": 0.04,
    "type": "Buy",
    "entryPrice": 4060.74,
    "tp": 4082.2,
    "sl": 4073.3,
    "closePrice": null,
    "grossProfit": 0,
    "pips": 0,
    "balance": null,
    "equity": 9960.28
  },
  {
    "serial": 27,
    "orderId": null,
    "positionId": 5,
    "event": "Stop Loss Hit",
    "time": 1782703420572,
    "volume": 4,
    "quantity": 0.04,
    "type": "Buy",
    "entryPrice": 4060.74,
    "tp": 4082.2,
    "sl": 4073.3,
    "closePrice": 4073.26,
    "grossProfit": 50.08,
    "pips": 1252,
    "balance": 9951.2,
    "equity": 9951.2
  },
  {
    "serial": 28,
    "orderId": null,
    "positionId": 6,
    "event": "Create Position",
    "time": 1782740700347,
    "volume": 6,
    "quantity": 0.06,
    "type": "Buy",
    "entryPrice": 4038.41,
    "tp": 4053.92,
    "sl": 4030.91,
    "closePrice": null,
    "grossProfit": 0,
    "pips": 0,
    "balance": null,
    "equity": 9951.2
  },
  {
    "serial": 29,
    "orderId": null,
    "positionId": 6,
    "event": "Stop Loss Hit",
    "time": 1782741276637,
    "volume": 6,
    "quantity": 0.06,
    "type": "Buy",
    "entryPrice": 4038.41,
    "tp": 4053.92,
    "sl": 4030.91,
    "closePrice": 4030.64,
    "grossProfit": -46.62,
    "pips": -776.9999999999999,
    "balance": 9903.140000000001,
    "equity": 9903.140000000001
  },
  {
    "serial": 30,
    "orderId": null,
    "positionId": 7,
    "event": "Create Position",
    "time": 1782924300060,
    "volume": 2,
    "quantity": 0.02,
    "type": "Sell",
    "entryPrice": 4074.1,
    "tp": 4036.37,
    "sl": 4093.63,
    "closePrice": null,
    "grossProfit": 0,
    "pips": 0,
    "balance": null,
    "equity": 9903.140000000001
  },
  {
    "serial": 31,
    "orderId": null,
    "positionId": 7,
    "event": "Position Modified (S/L)",
    "time": 1782935140185,
    "volume": 2,
    "quantity": 0.02,
    "type": "Sell",
    "entryPrice": 4074.1,
    "tp": 4036.37,
    "sl": 4056.33,
    "closePrice": null,
    "grossProfit": 0,
    "pips": 0,
    "balance": null,
    "equity": 9946.02
  },
  {
    "serial": 32,
    "orderId": null,
    "positionId": 7,
    "event": "Position Modified (S/L)",
    "time": 1782935140548,
    "volume": 2,
    "quantity": 0.02,
    "type": "Sell",
    "entryPrice": 4074.1,
    "tp": 4036.37,
    "sl": 4055.93,
    "closePrice": null,
    "grossProfit": 0,
    "pips": 0,
    "balance": null,
    "equity": 9946.820000000002
  },
  {
    "serial": 33,
    "orderId": null,
    "positionId": 7,
    "event": "Position Modified (S/L)",
    "time": 1782935140907,
    "volume": 2,
    "quantity": 0.02,
    "type": "Sell",
    "entryPrice": 4074.1,
    "tp": 4036.37,
    "sl": 4055.25,
    "closePrice": null,
    "grossProfit": 0,
    "pips": 0,
    "balance": null,
    "equity": 9948.180000000002
  },
  {
    "serial": 34,
    "orderId": null,
    "positionId": 7,
    "event": "Position Modified (S/L)",
    "time": 1782935415095,
    "volume": 2,
    "quantity": 0.02,
    "type": "Sell",
    "entryPrice": 4074.1,
    "tp": 4036.37,
    "sl": 4055.23,
    "closePrice": null,
    "grossProfit": 0,
    "pips": 0,
    "balance": null,
    "equity": 9948.220000000001
  },
  {
    "serial": 35,
    "orderId": null,
    "positionId": 7,
    "event": "Position Modified (S/L)",
    "time": 1782935416189,
    "volume": 2,
    "quantity": 0.02,
    "type": "Sell",
    "entryPrice": 4074.1,
    "tp": 4036.37,
    "sl": 4055.18,
    "closePrice": null,
    "grossProfit": 0,
    "pips": 0,
    "balance": null,
    "equity": 9948.320000000002
  },
  {
    "serial": 36,
    "orderId": null,
    "positionId": 7,
    "event": "Position Modified (S/L)",
    "time": 1782935416566,
    "volume": 2,
    "quantity": 0.02,
    "type": "Sell",
    "entryPrice": 4074.1,
    "tp": 4036.37,
    "sl": 4055.15,
    "closePrice": null,
    "grossProfit": 0,
    "pips": 0,
    "balance": null,
    "equity": 9948.380000000001
  },
  {
    "serial": 37,
    "orderId": null,
    "positionId": 7,
    "event": "Position Modified (S/L)",
    "time": 1782935422885,
    "volume": 2,
    "quantity": 0.02,
    "type": "Sell",
    "entryPrice": 4074.1,
    "tp": 4036.37,
    "sl": 4055.12,
    "closePrice": null,
    "grossProfit": 0,
    "pips": 0,
    "balance": null,
    "equity": 9948.44
  },
  {
    "serial": 38,
    "orderId": null,
    "positionId": 7,
    "event": "Position Modified (S/L)",
    "time": 1782935423259,
    "volume": 2,
    "quantity": 0.02,
    "type": "Sell",
    "entryPrice": 4074.1,
    "tp": 4036.37,
    "sl": 4055.03,
    "closePrice": null,
    "grossProfit": 0,
    "pips": 0,
    "balance": null,
    "equity": 9948.62
  },
  {
    "serial": 39,
    "orderId": null,
    "positionId": 7,
    "event": "Position Modified (S/L)",
    "time": 1782935423980,
    "volume": 2,
    "quantity": 0.02,
    "type": "Sell",
    "entryPrice": 4074.1,
    "tp": 4036.37,
    "sl": 4055,
    "closePrice": null,
    "grossProfit": 0,
    "pips": 0,
    "balance": null,
    "equity": 9948.680000000002
  },
  {
    "serial": 40,
    "orderId": null,
    "positionId": 7,
    "event": "Position Modified (S/L)",
    "time": 1782935424734,
    "volume": 2,
    "quantity": 0.02,
    "type": "Sell",
    "entryPrice": 4074.1,
    "tp": 4036.37,
    "sl": 4054.96,
    "closePrice": null,
    "grossProfit": 0,
    "pips": 0,
    "balance": null,
    "equity": 9948.760000000002
  },
  {
    "serial": 41,
    "orderId": null,
    "positionId": 7,
    "event": "Position Modified (S/L)",
    "time": 1782935425117,
    "volume": 2,
    "quantity": 0.02,
    "type": "Sell",
    "entryPrice": 4074.1,
    "tp": 4036.37,
    "sl": 4054.9,
    "closePrice": null,
    "grossProfit": 0,
    "pips": 0,
    "balance": null,
    "equity": 9948.880000000001
  },
  {
    "serial": 42,
    "orderId": null,
    "positionId": 7,
    "event": "Position Modified (S/L)",
    "time": 1782935425481,
    "volume": 2,
    "quantity": 0.02,
    "type": "Sell",
    "entryPrice": 4074.1,
    "tp": 4036.37,
    "sl": 4054.73,
    "closePrice": null,
    "grossProfit": 0,
    "pips": 0,
    "balance": null,
    "equity": 9949.220000000001
  },
  {
    "serial": 43,
    "orderId": null,
    "positionId": 7,
    "event": "Position Modified (S/L)",
    "time": 1782935425842,
    "volume": 2,
    "quantity": 0.02,
    "type": "Sell",
    "entryPrice": 4074.1,
    "tp": 4036.37,
    "sl": 4054.57,
    "closePrice": null,
    "grossProfit": 0,
    "pips": 0,
    "balance": null,
    "equity": 9949.54
  },
  {
    "serial": 44,
    "orderId": null,
    "positionId": 7,
    "event": "Position Modified (S/L)",
    "time": 1782935426194,
    "volume": 2,
    "quantity": 0.02,
    "type": "Sell",
    "entryPrice": 4074.1,
    "tp": 4036.37,
    "sl": 4054.41,
    "closePrice": null,
    "grossProfit": 0,
    "pips": 0,
    "balance": null,
    "equity": 9949.86
  },
  {
    "serial": 45,
    "orderId": null,
    "positionId": 7,
    "event": "Position Modified (S/L)",
    "time": 1782935426547,
    "volume": 2,
    "quantity": 0.02,
    "type": "Sell",
    "entryPrice": 4074.1,
    "tp": 4036.37,
    "sl": 4054.04,
    "closePrice": null,
    "grossProfit": 0,
    "pips": 0,
    "balance": null,
    "equity": 9950.6
  },
  {
    "serial": 46,
    "orderId": null,
    "positionId": 7,
    "event": "Position Modified (S/L)",
    "time": 1782935426899,
    "volume": 2,
    "quantity": 0.02,
    "type": "Sell",
    "entryPrice": 4074.1,
    "tp": 4036.37,
    "sl": 4052.96,
    "closePrice": null,
    "grossProfit": 0,
    "pips": 0,
    "balance": null,
    "equity": 9952.760000000002
  },
  {
    "serial": 47,
    "orderId": null,
    "positionId": 7,
    "event": "Position Modified (S/L)",
    "time": 1782935504575,
    "volume": 2,
    "quantity": 0.02,
    "type": "Sell",
    "entryPrice": 4074.1,
    "tp": 4036.37,
    "sl": 4052.88,
    "closePrice": null,
    "grossProfit": 0,
    "pips": 0,
    "balance": null,
    "equity": 9952.920000000002
  },
  {
    "serial": 48,
    "orderId": null,
    "positionId": 7,
    "event": "Position Modified (S/L)",
    "time": 1782935504940,
    "volume": 2,
    "quantity": 0.02,
    "type": "Sell",
    "entryPrice": 4074.1,
    "tp": 4036.37,
    "sl": 4052.85,
    "closePrice": null,
    "grossProfit": 0,
    "pips": 0,
    "balance": null,
    "equity": 9952.980000000001
  },
  {
    "serial": 49,
    "orderId": null,
    "positionId": 7,
    "event": "Position Modified (S/L)",
    "time": 1782935510810,
    "volume": 2,
    "quantity": 0.02,
    "type": "Sell",
    "entryPrice": 4074.1,
    "tp": 4036.37,
    "sl": 4052.81,
    "closePrice": null,
    "grossProfit": 0,
    "pips": 0,
    "balance": null,
    "equity": 9953.060000000001
  },
  {
    "serial": 50,
    "orderId": null,
    "positionId": 7,
    "event": "Position Modified (S/L)",
    "time": 1782935511535,
    "volume": 2,
    "quantity": 0.02,
    "type": "Sell",
    "entryPrice": 4074.1,
    "tp": 4036.37,
    "sl": 4052.76,
    "closePrice": null,
    "grossProfit": 0,
    "pips": 0,
    "balance": null,
    "equity": 9953.160000000002
  },
  {
    "serial": 51,
    "orderId": null,
    "positionId": 7,
    "event": "Position Modified (S/L)",
    "time": 1782935511886,
    "volume": 2,
    "quantity": 0.02,
    "type": "Sell",
    "entryPrice": 4074.1,
    "tp": 4036.37,
    "sl": 4052.71,
    "closePrice": null,
    "grossProfit": 0,
    "pips": 0,
    "balance": null,
    "equity": 9953.260000000002
  },
  {
    "serial": 52,
    "orderId": null,
    "positionId": 7,
    "event": "Position Modified (S/L)",
    "time": 1782935512271,
    "volume": 2,
    "quantity": 0.02,
    "type": "Sell",
    "entryPrice": 4074.1,
    "tp": 4036.37,
    "sl": 4052.26,
    "closePrice": null,
    "grossProfit": 0,
    "pips": 0,
    "balance": null,
    "equity": 9954.160000000002
  },
  {
    "serial": 53,
    "orderId": null,
    "positionId": 7,
    "event": "Position Modified (S/L)",
    "time": 1782935512642,
    "volume": 2,
    "quantity": 0.02,
    "type": "Sell",
    "entryPrice": 4074.1,
    "tp": 4036.37,
    "sl": 4052.22,
    "closePrice": null,
    "grossProfit": 0,
    "pips": 0,
    "balance": null,
    "equity": 9954.240000000002
  },
  {
    "serial": 54,
    "orderId": null,
    "positionId": 7,
    "event": "Position Modified (S/L)",
    "time": 1782935513357,
    "volume": 2,
    "quantity": 0.02,
    "type": "Sell",
    "entryPrice": 4074.1,
    "tp": 4036.37,
    "sl": 4052.16,
    "closePrice": null,
    "grossProfit": 0,
    "pips": 0,
    "balance": null,
    "equity": 9954.36
  },
  {
    "serial": 55,
    "orderId": null,
    "positionId": 7,
    "event": "Position Modified (S/L)",
    "time": 1782935513715,
    "volume": 2,
    "quantity": 0.02,
    "type": "Sell",
    "entryPrice": 4074.1,
    "tp": 4036.37,
    "sl": 4052.13,
    "closePrice": null,
    "grossProfit": 0,
    "pips": 0,
    "balance": null,
    "equity": 9954.420000000002
  },
  {
    "serial": 56,
    "orderId": null,
    "positionId": 7,
    "event": "Position Modified (S/L)",
    "time": 1782935515544,
    "volume": 2,
    "quantity": 0.02,
    "type": "Sell",
    "entryPrice": 4074.1,
    "tp": 4036.37,
    "sl": 4052.08,
    "closePrice": null,
    "grossProfit": 0,
    "pips": 0,
    "balance": null,
    "equity": 9954.52
  },
  {
    "serial": 57,
    "orderId": null,
    "positionId": 7,
    "event": "Position Modified (S/L)",
    "time": 1782935516673,
    "volume": 2,
    "quantity": 0.02,
    "type": "Sell",
    "entryPrice": 4074.1,
    "tp": 4036.37,
    "sl": 4051.92,
    "closePrice": null,
    "grossProfit": 0,
    "pips": 0,
    "balance": null,
    "equity": 9954.840000000002
  },
  {
    "serial": 58,
    "orderId": null,
    "positionId": 7,
    "event": "Position Modified (S/L)",
    "time": 1782935517049,
    "volume": 2,
    "quantity": 0.02,
    "type": "Sell",
    "entryPrice": 4074.1,
    "tp": 4036.37,
    "sl": 4051.6,
    "closePrice": null,
    "grossProfit": 0,
    "pips": 0,
    "balance": null,
    "equity": 9955.480000000001
  },
  {
    "serial": 59,
    "orderId": null,
    "positionId": 7,
    "event": "Position Modified (S/L)",
    "time": 1782935517419,
    "volume": 2,
    "quantity": 0.02,
    "type": "Sell",
    "entryPrice": 4074.1,
    "tp": 4036.37,
    "sl": 4051.37,
    "closePrice": null,
    "grossProfit": 0,
    "pips": 0,
    "balance": null,
    "equity": 9955.94
  },
  {
    "serial": 60,
    "orderId": null,
    "positionId": 7,
    "event": "Position Modified (S/L)",
    "time": 1782935518158,
    "volume": 2,
    "quantity": 0.02,
    "type": "Sell",
    "entryPrice": 4074.1,
    "tp": 4036.37,
    "sl": 4051.08,
    "closePrice": null,
    "grossProfit": 0,
    "pips": 0,
    "balance": null,
    "equity": 9956.52
  },
  {
    "serial": 61,
    "orderId": null,
    "positionId": 7,
    "event": "Position Modified (S/L)",
    "time": 1782935518522,
    "volume": 2,
    "quantity": 0.02,
    "type": "Sell",
    "entryPrice": 4074.1,
    "tp": 4036.37,
    "sl": 4050.91,
    "closePrice": null,
    "grossProfit": 0,
    "pips": 0,
    "balance": null,
    "equity": 9956.86
  },
  {
    "serial": 62,
    "orderId": null,
    "positionId": 7,
    "event": "Position Modified (S/L)",
    "time": 1782935518910,
    "volume": 2,
    "quantity": 0.02,
    "type": "Sell",
    "entryPrice": 4074.1,
    "tp": 4036.37,
    "sl": 4050.68,
    "closePrice": null,
    "grossProfit": 0,
    "pips": 0,
    "balance": null,
    "equity": 9957.320000000002
  },
  {
    "serial": 63,
    "orderId": null,
    "positionId": 7,
    "event": "Position Modified (S/L)",
    "time": 1782935519267,
    "volume": 2,
    "quantity": 0.02,
    "type": "Sell",
    "entryPrice": 4074.1,
    "tp": 4036.37,
    "sl": 4050.01,
    "closePrice": null,
    "grossProfit": 0,
    "pips": 0,
    "balance": null,
    "equity": 9958.660000000002
  },
  {
    "serial": 64,
    "orderId": null,
    "positionId": 7,
    "event": "Position Modified (S/L)",
    "time": 1782935520000,
    "volume": 2,
    "quantity": 0.02,
    "type": "Sell",
    "entryPrice": 4074.1,
    "tp": 4036.37,
    "sl": 4049.99,
    "closePrice": null,
    "grossProfit": 0,
    "pips": 0,
    "balance": null,
    "equity": 9958.7
  },
  {
    "serial": 65,
    "orderId": null,
    "positionId": 7,
    "event": "Position Modified (S/L)",
    "time": 1782935520724,
    "volume": 2,
    "quantity": 0.02,
    "type": "Sell",
    "entryPrice": 4074.1,
    "tp": 4036.37,
    "sl": 4049.88,
    "closePrice": null,
    "grossProfit": 0,
    "pips": 0,
    "balance": null,
    "equity": 9958.920000000002
  },
  {
    "serial": 66,
    "orderId": null,
    "positionId": 7,
    "event": "Position Modified (S/L)",
    "time": 1782935521084,
    "volume": 2,
    "quantity": 0.02,
    "type": "Sell",
    "entryPrice": 4074.1,
    "tp": 4036.37,
    "sl": 4049.86,
    "closePrice": null,
    "grossProfit": 0,
    "pips": 0,
    "balance": null,
    "equity": 9958.960000000001
  },
  {
    "serial": 67,
    "orderId": null,
    "positionId": 7,
    "event": "Position Modified (S/L)",
    "time": 1782935521437,
    "volume": 2,
    "quantity": 0.02,
    "type": "Sell",
    "entryPrice": 4074.1,
    "tp": 4036.37,
    "sl": 4049.45,
    "closePrice": null,
    "grossProfit": 0,
    "pips": 0,
    "balance": null,
    "equity": 9959.78
  },
  {
    "serial": 68,
    "orderId": null,
    "positionId": 7,
    "event": "Position Modified (S/L)",
    "time": 1782935521787,
    "volume": 2,
    "quantity": 0.02,
    "type": "Sell",
    "entryPrice": 4074.1,
    "tp": 4036.37,
    "sl": 4048.78,
    "closePrice": null,
    "grossProfit": 0,
    "pips": 0,
    "balance": null,
    "equity": 9961.12
  },
  {
    "serial": 69,
    "orderId": null,
    "positionId": 7,
    "event": "Position Modified (S/L)",
    "time": 1782935522177,
    "volume": 2,
    "quantity": 0.02,
    "type": "Sell",
    "entryPrice": 4074.1,
    "tp": 4036.37,
    "sl": 4048.52,
    "closePrice": null,
    "grossProfit": 0,
    "pips": 0,
    "balance": null,
    "equity": 9961.640000000001
  },
  {
    "serial": 70,
    "orderId": null,
    "positionId": 7,
    "event": "Position Modified (S/L)",
    "time": 1782935523640,
    "volume": 2,
    "quantity": 0.02,
    "type": "Sell",
    "entryPrice": 4074.1,
    "tp": 4036.37,
    "sl": 4047.57,
    "closePrice": null,
    "grossProfit": 0,
    "pips": 0,
    "balance": null,
    "equity": 9963.54
  },
  {
    "serial": 71,
    "orderId": null,
    "positionId": 7,
    "event": "Position Modified (S/L)",
    "time": 1782935523993,
    "volume": 2,
    "quantity": 0.02,
    "type": "Sell",
    "entryPrice": 4074.1,
    "tp": 4036.37,
    "sl": 4047.49,
    "closePrice": null,
    "grossProfit": 0,
    "pips": 0,
    "balance": null,
    "equity": 9963.7
  },
  {
    "serial": 72,
    "orderId": null,
    "positionId": 7,
    "event": "Position Modified (S/L)",
    "time": 1782935524349,
    "volume": 2,
    "quantity": 0.02,
    "type": "Sell",
    "entryPrice": 4074.1,
    "tp": 4036.37,
    "sl": 4047.39,
    "closePrice": null,
    "grossProfit": 0,
    "pips": 0,
    "balance": null,
    "equity": 9963.900000000001
  },
  {
    "serial": 73,
    "orderId": null,
    "positionId": 7,
    "event": "Position Modified (S/L)",
    "time": 1782935526206,
    "volume": 2,
    "quantity": 0.02,
    "type": "Sell",
    "entryPrice": 4074.1,
    "tp": 4036.37,
    "sl": 4047.24,
    "closePrice": null,
    "grossProfit": 0,
    "pips": 0,
    "balance": null,
    "equity": 9964.2
  },
  {
    "serial": 74,
    "orderId": null,
    "positionId": 7,
    "event": "Position Modified (S/L)",
    "time": 1782935526560,
    "volume": 2,
    "quantity": 0.02,
    "type": "Sell",
    "entryPrice": 4074.1,
    "tp": 4036.37,
    "sl": 4047.17,
    "closePrice": null,
    "grossProfit": 0,
    "pips": 0,
    "balance": null,
    "equity": 9964.340000000002
  },
  {
    "serial": 75,
    "orderId": null,
    "positionId": 7,
    "event": "Position Modified (S/L)",
    "time": 1782935527276,
    "volume": 2,
    "quantity": 0.02,
    "type": "Sell",
    "entryPrice": 4074.1,
    "tp": 4036.37,
    "sl": 4046.27,
    "closePrice": null,
    "grossProfit": 0,
    "pips": 0,
    "balance": null,
    "equity": 9966.140000000001
  },
  {
    "serial": 76,
    "orderId": null,
    "positionId": 7,
    "event": "Position Modified (S/L)",
    "time": 1782935527641,
    "volume": 2,
    "quantity": 0.02,
    "type": "Sell",
    "entryPrice": 4074.1,
    "tp": 4036.37,
    "sl": 4045.95,
    "closePrice": null,
    "grossProfit": 0,
    "pips": 0,
    "balance": null,
    "equity": 9966.78
  },
  {
    "serial": 77,
    "orderId": null,
    "positionId": 7,
    "event": "Position Modified (S/L)",
    "time": 1782935531284,
    "volume": 2,
    "quantity": 0.02,
    "type": "Sell",
    "entryPrice": 4074.1,
    "tp": 4036.37,
    "sl": 4044.88,
    "closePrice": null,
    "grossProfit": 0,
    "pips": 0,
    "balance": null,
    "equity": 9968.920000000002
  },
  {
    "serial": 78,
    "orderId": null,
    "positionId": 7,
    "event": "Position Modified (S/L)",
    "time": 1782935531668,
    "volume": 2,
    "quantity": 0.02,
    "type": "Sell",
    "entryPrice": 4074.1,
    "tp": 4036.37,
    "sl": 4044.59,
    "closePrice": null,
    "grossProfit": 0,
    "pips": 0,
    "balance": null,
    "equity": 9969.500000000002
  },
  {
    "serial": 79,
    "orderId": null,
    "positionId": 7,
    "event": "Position Modified (S/L)",
    "time": 1782935533078,
    "volume": 2,
    "quantity": 0.02,
    "type": "Sell",
    "entryPrice": 4074.1,
    "tp": 4036.37,
    "sl": 4044.48,
    "closePrice": null,
    "grossProfit": 0,
    "pips": 0,
    "balance": null,
    "equity": 9969.720000000001
  },
  {
    "serial": 80,
    "orderId": null,
    "positionId": 7,
    "event": "Position Modified (S/L)",
    "time": 1782935533429,
    "volume": 2,
    "quantity": 0.02,
    "type": "Sell",
    "entryPrice": 4074.1,
    "tp": 4036.37,
    "sl": 4044.26,
    "closePrice": null,
    "grossProfit": 0,
    "pips": 0,
    "balance": null,
    "equity": 9970.160000000002
  },
  {
    "serial": 81,
    "orderId": null,
    "positionId": 7,
    "event": "Position Modified (S/L)",
    "time": 1782935533782,
    "volume": 2,
    "quantity": 0.02,
    "type": "Sell",
    "entryPrice": 4074.1,
    "tp": 4036.37,
    "sl": 4043.62,
    "closePrice": null,
    "grossProfit": 0,
    "pips": 0,
    "balance": null,
    "equity": 9971.44
  },
  {
    "serial": 82,
    "orderId": null,
    "positionId": 7,
    "event": "Position Modified (S/L)",
    "time": 1782935535546,
    "volume": 2,
    "quantity": 0.02,
    "type": "Sell",
    "entryPrice": 4074.1,
    "tp": 4036.37,
    "sl": 4043.47,
    "closePrice": null,
    "grossProfit": 0,
    "pips": 0,
    "balance": null,
    "equity": 9971.740000000002
  },
  {
    "serial": 83,
    "orderId": null,
    "positionId": 7,
    "event": "Position Modified (S/L)",
    "time": 1782935535906,
    "volume": 2,
    "quantity": 0.02,
    "type": "Sell",
    "entryPrice": 4074.1,
    "tp": 4036.37,
    "sl": 4043.26,
    "closePrice": null,
    "grossProfit": 0,
    "pips": 0,
    "balance": null,
    "equity": 9972.160000000002
  },
  {
    "serial": 84,
    "orderId": null,
    "positionId": 7,
    "event": "Position Modified (S/L)",
    "time": 1782935768489,
    "volume": 2,
    "quantity": 0.02,
    "type": "Sell",
    "entryPrice": 4074.1,
    "tp": 4036.37,
    "sl": 4043.19,
    "closePrice": null,
    "grossProfit": 0,
    "pips": 0,
    "balance": null,
    "equity": 9972.300000000001
  },
  {
    "serial": 85,
    "orderId": null,
    "positionId": 7,
    "event": "Position Modified (S/L)",
    "time": 1782935776163,
    "volume": 2,
    "quantity": 0.02,
    "type": "Sell",
    "entryPrice": 4074.1,
    "tp": 4036.37,
    "sl": 4042.98,
    "closePrice": null,
    "grossProfit": 0,
    "pips": 0,
    "balance": null,
    "equity": 9972.720000000001
  },
  {
    "serial": 86,
    "orderId": null,
    "positionId": 7,
    "event": "Position Modified (S/L)",
    "time": 1782935776543,
    "volume": 2,
    "quantity": 0.02,
    "type": "Sell",
    "entryPrice": 4074.1,
    "tp": 4036.37,
    "sl": 4042.96,
    "closePrice": null,
    "grossProfit": 0,
    "pips": 0,
    "balance": null,
    "equity": 9972.760000000002
  },
  {
    "serial": 87,
    "orderId": null,
    "positionId": 7,
    "event": "Position Modified (S/L)",
    "time": 1782935776928,
    "volume": 2,
    "quantity": 0.02,
    "type": "Sell",
    "entryPrice": 4074.1,
    "tp": 4036.37,
    "sl": 4042.95,
    "closePrice": null,
    "grossProfit": 0,
    "pips": 0,
    "balance": null,
    "equity": 9972.78
  },
  {
    "serial": 88,
    "orderId": null,
    "positionId": 7,
    "event": "Position Modified (S/L)",
    "time": 1782935777654,
    "volume": 2,
    "quantity": 0.02,
    "type": "Sell",
    "entryPrice": 4074.1,
    "tp": 4036.37,
    "sl": 4042.93,
    "closePrice": null,
    "grossProfit": 0,
    "pips": 0,
    "balance": null,
    "equity": 9972.820000000002
  },
  {
    "serial": 89,
    "orderId": null,
    "positionId": 7,
    "event": "Position Modified (S/L)",
    "time": 1782935778734,
    "volume": 2,
    "quantity": 0.02,
    "type": "Sell",
    "entryPrice": 4074.1,
    "tp": 4036.37,
    "sl": 4042.91,
    "closePrice": null,
    "grossProfit": 0,
    "pips": 0,
    "balance": null,
    "equity": 9972.86
  },
  {
    "serial": 90,
    "orderId": null,
    "positionId": 7,
    "event": "Position Modified (S/L)",
    "time": 1782935779095,
    "volume": 2,
    "quantity": 0.02,
    "type": "Sell",
    "entryPrice": 4074.1,
    "tp": 4036.37,
    "sl": 4042.66,
    "closePrice": null,
    "grossProfit": 0,
    "pips": 0,
    "balance": null,
    "equity": 9973.36
  },
  {
    "serial": 91,
    "orderId": null,
    "positionId": 7,
    "event": "Position Modified (S/L)",
    "time": 1782935779465,
    "volume": 2,
    "quantity": 0.02,
    "type": "Sell",
    "entryPrice": 4074.1,
    "tp": 4036.37,
    "sl": 4041.68,
    "closePrice": null,
    "grossProfit": 0,
    "pips": 0,
    "balance": null,
    "equity": 9975.320000000002
  },
  {
    "serial": 92,
    "orderId": null,
    "positionId": 7,
    "event": "Position Modified (S/L)",
    "time": 1782935781330,
    "volume": 2,
    "quantity": 0.02,
    "type": "Sell",
    "entryPrice": 4074.1,
    "tp": 4036.37,
    "sl": 4041.22,
    "closePrice": null,
    "grossProfit": 0,
    "pips": 0,
    "balance": null,
    "equity": 9976.240000000002
  },
  {
    "serial": 93,
    "orderId": null,
    "positionId": 7,
    "event": "Position Modified (S/L)",
    "time": 1782935824878,
    "volume": 2,
    "quantity": 0.02,
    "type": "Sell",
    "entryPrice": 4074.1,
    "tp": 4036.37,
    "sl": 4041.18,
    "closePrice": null,
    "grossProfit": 0,
    "pips": 0,
    "balance": null,
    "equity": 9976.320000000002
  },
  {
    "serial": 94,
    "orderId": null,
    "positionId": 7,
    "event": "Take Profit Hit",
    "time": 1782935825271,
    "volume": 2,
    "quantity": 0.02,
    "type": "Sell",
    "entryPrice": 4074.1,
    "tp": 4036.37,
    "sl": 4041.18,
    "closePrice": 4036.23,
    "grossProfit": 75.74,
    "pips": 3786.9999999999995,
    "balance": 9978.400000000001,
    "equity": 9978.400000000001
  },
  {
    "serial": 95,
    "orderId": null,
    "positionId": 8,
    "event": "Create Position",
    "time": 1783008900394,
    "volume": 3,
    "quantity": 0.03,
    "type": "Sell",
    "entryPrice": 4123.56,
    "tp": 4097.650000000001,
    "sl": 4136.31,
    "closePrice": null,
    "grossProfit": 0,
    "pips": 0,
    "balance": null,
    "equity": 9978.400000000001
  },
  {
    "serial": 96,
    "orderId": null,
    "positionId": 8,
    "event": "Position Modified (S/L, T/P)",
    "time": 1783009830603,
    "volume": 3,
    "quantity": 0.03,
    "type": "Sell",
    "entryPrice": 4123.56,
    "tp": 4097.64,
    "sl": 4111.76,
    "closePrice": null,
    "grossProfit": 0,
    "pips": 0,
    "balance": null,
    "equity": 10020.730000000001
  },
  {
    "serial": 97,
    "orderId": null,
    "positionId": 8,
    "event": "Position Modified (S/L)",
    "time": 1783009830991,
    "volume": 3,
    "quantity": 0.03,
    "type": "Sell",
    "entryPrice": 4123.56,
    "tp": 4097.64,
    "sl": 4111.47,
    "closePrice": null,
    "grossProfit": 0,
    "pips": 0,
    "balance": null,
    "equity": 10021.600000000002
  },
  {
    "serial": 98,
    "orderId": null,
    "positionId": 8,
    "event": "Position Modified (S/L)",
    "time": 1783009834997,
    "volume": 3,
    "quantity": 0.03,
    "type": "Sell",
    "entryPrice": 4123.56,
    "tp": 4097.64,
    "sl": 4111.42,
    "closePrice": null,
    "grossProfit": 0,
    "pips": 0,
    "balance": null,
    "equity": 10021.750000000002
  },
  {
    "serial": 99,
    "orderId": null,
    "positionId": 8,
    "event": "Position Modified (S/L)",
    "time": 1783009835348,
    "volume": 3,
    "quantity": 0.03,
    "type": "Sell",
    "entryPrice": 4123.56,
    "tp": 4097.64,
    "sl": 4110.43,
    "closePrice": null,
    "grossProfit": 0,
    "pips": 0,
    "balance": null,
    "equity": 10024.690000000002
  },
  {
    "serial": 100,
    "orderId": null,
    "positionId": 8,
    "event": "Position Modified (S/L)",
    "time": 1783009835725,
    "volume": 3,
    "quantity": 0.03,
    "type": "Sell",
    "entryPrice": 4123.56,
    "tp": 4097.64,
    "sl": 4110.25,
    "closePrice": null,
    "grossProfit": 0,
    "pips": 0,
    "balance": null,
    "equity": 10025.260000000002
  },
  {
    "serial": 101,
    "orderId": null,
    "positionId": 8,
    "event": "Position Modified (S/L)",
    "time": 1783009836432,
    "volume": 3,
    "quantity": 0.03,
    "type": "Sell",
    "entryPrice": 4123.56,
    "tp": 4097.64,
    "sl": 4109.6,
    "closePrice": null,
    "grossProfit": 0,
    "pips": 0,
    "balance": null,
    "equity": 10027.180000000002
  },
  {
    "serial": 102,
    "orderId": null,
    "positionId": 8,
    "event": "Position Modified (S/L)",
    "time": 1783009836790,
    "volume": 3,
    "quantity": 0.03,
    "type": "Sell",
    "entryPrice": 4123.56,
    "tp": 4097.64,
    "sl": 4109.52,
    "closePrice": null,
    "grossProfit": 0,
    "pips": 0,
    "balance": null,
    "equity": 10027.45
  },
  {
    "serial": 103,
    "orderId": null,
    "positionId": 8,
    "event": "Stop Loss Hit",
    "time": 1783009852184,
    "volume": 3,
    "quantity": 0.03,
    "type": "Sell",
    "entryPrice": 4123.56,
    "tp": 4097.64,
    "sl": 4109.52,
    "closePrice": 4109.56,
    "grossProfit": 42,
    "pips": 1400,
    "balance": 10019.680000000002,
    "equity": 10019.680000000002
  },
  {
    "serial": 104,
    "orderId": null,
    "positionId": 9,
    "event": "Create Position",
    "time": 1783016100262,
    "volume": 3,
    "quantity": 0.03,
    "type": "Buy",
    "entryPrice": 4119.38,
    "tp": 4151.93,
    "sl": 4102.86,
    "closePrice": null,
    "grossProfit": 0,
    "pips": 0,
    "balance": null,
    "equity": 10019.680000000002
  },
  {
    "serial": 105,
    "orderId": null,
    "positionId": 9,
    "event": "Position Modified (S/L)",
    "time": 1783038080571,
    "volume": 3,
    "quantity": 0.03,
    "type": "Buy",
    "entryPrice": 4119.38,
    "tp": 4151.93,
    "sl": 4134.26,
    "closePrice": null,
    "grossProfit": 0,
    "pips": 0,
    "balance": null,
    "equity": 10071.910000000002
  },
  {
    "serial": 106,
    "orderId": null,
    "positionId": 9,
    "event": "Position Modified (S/L)",
    "time": 1783038080927,
    "volume": 3,
    "quantity": 0.03,
    "type": "Buy",
    "entryPrice": 4119.38,
    "tp": 4151.93,
    "sl": 4134.5,
    "closePrice": null,
    "grossProfit": 0,
    "pips": 0,
    "balance": null,
    "equity": 10072.630000000003
  },
  {
    "serial": 107,
    "orderId": null,
    "positionId": 9,
    "event": "Position Modified (S/L)",
    "time": 1783038081290,
    "volume": 3,
    "quantity": 0.03,
    "type": "Buy",
    "entryPrice": 4119.38,
    "tp": 4151.93,
    "sl": 4134.64,
    "closePrice": null,
    "grossProfit": 0,
    "pips": 0,
    "balance": null,
    "equity": 10073.050000000003
  },
  {
    "serial": 108,
    "orderId": null,
    "positionId": 9,
    "event": "Position Modified (S/L)",
    "time": 1783038081643,
    "volume": 3,
    "quantity": 0.03,
    "type": "Buy",
    "entryPrice": 4119.38,
    "tp": 4151.93,
    "sl": 4134.71,
    "closePrice": null,
    "grossProfit": 0,
    "pips": 0,
    "balance": null,
    "equity": 10073.260000000002
  },
  {
    "serial": 109,
    "orderId": null,
    "positionId": 9,
    "event": "Position Modified (S/L)",
    "time": 1783038126500,
    "volume": 3,
    "quantity": 0.03,
    "type": "Buy",
    "entryPrice": 4119.38,
    "tp": 4151.93,
    "sl": 4134.77,
    "closePrice": null,
    "grossProfit": 0,
    "pips": 0,
    "balance": null,
    "equity": 10073.440000000002
  },
  {
    "serial": 110,
    "orderId": null,
    "positionId": 9,
    "event": "Position Modified (S/L)",
    "time": 1783038129461,
    "volume": 3,
    "quantity": 0.03,
    "type": "Buy",
    "entryPrice": 4119.38,
    "tp": 4151.93,
    "sl": 4134.87,
    "closePrice": null,
    "grossProfit": 0,
    "pips": 0,
    "balance": null,
    "equity": 10073.740000000002
  },
  {
    "serial": 111,
    "orderId": null,
    "positionId": 9,
    "event": "Position Modified (S/L)",
    "time": 1783038129829,
    "volume": 3,
    "quantity": 0.03,
    "type": "Buy",
    "entryPrice": 4119.38,
    "tp": 4151.93,
    "sl": 4134.93,
    "closePrice": null,
    "grossProfit": 0,
    "pips": 0,
    "balance": null,
    "equity": 10073.920000000002
  },
  {
    "serial": 112,
    "orderId": null,
    "positionId": 9,
    "event": "Position Modified (S/L)",
    "time": 1783038133075,
    "volume": 3,
    "quantity": 0.03,
    "type": "Buy",
    "entryPrice": 4119.38,
    "tp": 4151.93,
    "sl": 4134.97,
    "closePrice": null,
    "grossProfit": 0,
    "pips": 0,
    "balance": null,
    "equity": 10074.040000000003
  },
  {
    "serial": 113,
    "orderId": null,
    "positionId": 9,
    "event": "Position Modified (S/L)",
    "time": 1783038134836,
    "volume": 3,
    "quantity": 0.03,
    "type": "Buy",
    "entryPrice": 4119.38,
    "tp": 4151.93,
    "sl": 4135.01,
    "closePrice": null,
    "grossProfit": 0,
    "pips": 0,
    "balance": null,
    "equity": 10074.160000000002
  },
  {
    "serial": 114,
    "orderId": null,
    "positionId": 9,
    "event": "Position Modified (S/L)",
    "time": 1783038154850,
    "volume": 3,
    "quantity": 0.03,
    "type": "Buy",
    "entryPrice": 4119.38,
    "tp": 4151.93,
    "sl": 4135.14,
    "closePrice": null,
    "grossProfit": 0,
    "pips": 0,
    "balance": null,
    "equity": 10074.580000000002
  },
  {
    "serial": 115,
    "orderId": null,
    "positionId": 9,
    "event": "Position Modified (S/L)",
    "time": 1783038155208,
    "volume": 3,
    "quantity": 0.03,
    "type": "Buy",
    "entryPrice": 4119.38,
    "tp": 4151.93,
    "sl": 4135.16,
    "closePrice": null,
    "grossProfit": 0,
    "pips": 0,
    "balance": null,
    "equity": 10074.610000000002
  },
  {
    "serial": 116,
    "orderId": null,
    "positionId": 9,
    "event": "Position Modified (S/L)",
    "time": 1783038155558,
    "volume": 3,
    "quantity": 0.03,
    "type": "Buy",
    "entryPrice": 4119.38,
    "tp": 4151.93,
    "sl": 4135.17,
    "closePrice": null,
    "grossProfit": 0,
    "pips": 0,
    "balance": null,
    "equity": 10074.640000000001
  },
  {
    "serial": 117,
    "orderId": null,
    "positionId": 9,
    "event": "Position Modified (S/L)",
    "time": 1783038192373,
    "volume": 3,
    "quantity": 0.03,
    "type": "Buy",
    "entryPrice": 4119.38,
    "tp": 4151.93,
    "sl": 4135.18,
    "closePrice": null,
    "grossProfit": 0,
    "pips": 0,
    "balance": null,
    "equity": 10074.700000000003
  },
  {
    "serial": 118,
    "orderId": null,
    "positionId": 9,
    "event": "Position Modified (S/L)",
    "time": 1783038194488,
    "volume": 3,
    "quantity": 0.03,
    "type": "Buy",
    "entryPrice": 4119.38,
    "tp": 4151.93,
    "sl": 4135.35,
    "closePrice": null,
    "grossProfit": 0,
    "pips": 0,
    "balance": null,
    "equity": 10075.210000000003
  },
  {
    "serial": 119,
    "orderId": null,
    "positionId": 9,
    "event": "Position Modified (S/L)",
    "time": 1783038194848,
    "volume": 3,
    "quantity": 0.03,
    "type": "Buy",
    "entryPrice": 4119.38,
    "tp": 4151.93,
    "sl": 4135.42,
    "closePrice": null,
    "grossProfit": 0,
    "pips": 0,
    "balance": null,
    "equity": 10075.390000000001
  },
  {
    "serial": 120,
    "orderId": null,
    "positionId": 9,
    "event": "Position Modified (S/L)",
    "time": 1783038195203,
    "volume": 3,
    "quantity": 0.03,
    "type": "Buy",
    "entryPrice": 4119.38,
    "tp": 4151.93,
    "sl": 4135.46,
    "closePrice": null,
    "grossProfit": 0,
    "pips": 0,
    "balance": null,
    "equity": 10075.510000000002
  },
  {
    "serial": 121,
    "orderId": null,
    "positionId": 9,
    "event": "Position Modified (S/L)",
    "time": 1783038195569,
    "volume": 3,
    "quantity": 0.03,
    "type": "Buy",
    "entryPrice": 4119.38,
    "tp": 4151.93,
    "sl": 4135.55,
    "closePrice": null,
    "grossProfit": 0,
    "pips": 0,
    "balance": null,
    "equity": 10075.780000000002
  },
  {
    "serial": 122,
    "orderId": null,
    "positionId": 9,
    "event": "Position Modified (S/L)",
    "time": 1783038195933,
    "volume": 3,
    "quantity": 0.03,
    "type": "Buy",
    "entryPrice": 4119.38,
    "tp": 4151.93,
    "sl": 4135.62,
    "closePrice": null,
    "grossProfit": 0,
    "pips": 0,
    "balance": null,
    "equity": 10075.990000000002
  },
  {
    "serial": 123,
    "orderId": null,
    "positionId": 9,
    "event": "Position Modified (S/L)",
    "time": 1783038196306,
    "volume": 3,
    "quantity": 0.03,
    "type": "Buy",
    "entryPrice": 4119.38,
    "tp": 4151.93,
    "sl": 4135.67,
    "closePrice": null,
    "grossProfit": 0,
    "pips": 0,
    "balance": null,
    "equity": 10076.140000000001
  },
  {
    "serial": 124,
    "orderId": null,
    "positionId": 9,
    "event": "Position Modified (S/L)",
    "time": 1783038215473,
    "volume": 3,
    "quantity": 0.03,
    "type": "Buy",
    "entryPrice": 4119.38,
    "tp": 4151.93,
    "sl": 4135.71,
    "closePrice": null,
    "grossProfit": 0,
    "pips": 0,
    "balance": null,
    "equity": 10076.260000000002
  },
  {
    "serial": 125,
    "orderId": null,
    "positionId": 9,
    "event": "Position Modified (S/L)",
    "time": 1783038215832,
    "volume": 3,
    "quantity": 0.03,
    "type": "Buy",
    "entryPrice": 4119.38,
    "tp": 4151.93,
    "sl": 4135.72,
    "closePrice": null,
    "grossProfit": 0,
    "pips": 0,
    "balance": null,
    "equity": 10076.290000000003
  },
  {
    "serial": 126,
    "orderId": null,
    "positionId": 9,
    "event": "Position Modified (S/L)",
    "time": 1783038216185,
    "volume": 3,
    "quantity": 0.03,
    "type": "Buy",
    "entryPrice": 4119.38,
    "tp": 4151.93,
    "sl": 4135.85,
    "closePrice": null,
    "grossProfit": 0,
    "pips": 0,
    "balance": null,
    "equity": 10076.680000000002
  },
  {
    "serial": 127,
    "orderId": null,
    "positionId": 9,
    "event": "Position Modified (S/L)",
    "time": 1783038216543,
    "volume": 3,
    "quantity": 0.03,
    "type": "Buy",
    "entryPrice": 4119.38,
    "tp": 4151.93,
    "sl": 4135.88,
    "closePrice": null,
    "grossProfit": 0,
    "pips": 0,
    "balance": null,
    "equity": 10076.770000000002
  },
  {
    "serial": 128,
    "orderId": null,
    "positionId": 9,
    "event": "Position Modified (S/L)",
    "time": 1783038217248,
    "volume": 3,
    "quantity": 0.03,
    "type": "Buy",
    "entryPrice": 4119.38,
    "tp": 4151.93,
    "sl": 4135.91,
    "closePrice": null,
    "grossProfit": 0,
    "pips": 0,
    "balance": null,
    "equity": 10076.860000000002
  },
  {
    "serial": 129,
    "orderId": null,
    "positionId": 9,
    "event": "Position Modified (S/L)",
    "time": 1783038218670,
    "volume": 3,
    "quantity": 0.03,
    "type": "Buy",
    "entryPrice": 4119.38,
    "tp": 4151.93,
    "sl": 4135.97,
    "closePrice": null,
    "grossProfit": 0,
    "pips": 0,
    "balance": null,
    "equity": 10077.040000000003
  },
  {
    "serial": 130,
    "orderId": null,
    "positionId": 9,
    "event": "Position Modified (S/L)",
    "time": 1783038219735,
    "volume": 3,
    "quantity": 0.03,
    "type": "Buy",
    "entryPrice": 4119.38,
    "tp": 4151.93,
    "sl": 4136.18,
    "closePrice": null,
    "grossProfit": 0,
    "pips": 0,
    "balance": null,
    "equity": 10077.670000000002
  },
  {
    "serial": 131,
    "orderId": null,
    "positionId": 9,
    "event": "Position Modified (S/L)",
    "time": 1783038220087,
    "volume": 3,
    "quantity": 0.03,
    "type": "Buy",
    "entryPrice": 4119.38,
    "tp": 4151.93,
    "sl": 4136.27,
    "closePrice": null,
    "grossProfit": 0,
    "pips": 0,
    "balance": null,
    "equity": 10077.940000000002
  },
  {
    "serial": 132,
    "orderId": null,
    "positionId": 9,
    "event": "Position Modified (S/L)",
    "time": 1783038220447,
    "volume": 3,
    "quantity": 0.03,
    "type": "Buy",
    "entryPrice": 4119.38,
    "tp": 4151.93,
    "sl": 4136.39,
    "closePrice": null,
    "grossProfit": 0,
    "pips": 0,
    "balance": null,
    "equity": 10078.330000000002
  },
  {
    "serial": 133,
    "orderId": null,
    "positionId": 9,
    "event": "Position Modified (S/L)",
    "time": 1783038220797,
    "volume": 3,
    "quantity": 0.03,
    "type": "Buy",
    "entryPrice": 4119.38,
    "tp": 4151.93,
    "sl": 4136.42,
    "closePrice": null,
    "grossProfit": 0,
    "pips": 0,
    "balance": null,
    "equity": 10078.390000000001
  },
  {
    "serial": 134,
    "orderId": null,
    "positionId": 9,
    "event": "Position Modified (S/L)",
    "time": 1783038221891,
    "volume": 3,
    "quantity": 0.03,
    "type": "Buy",
    "entryPrice": 4119.38,
    "tp": 4151.93,
    "sl": 4136.43,
    "closePrice": null,
    "grossProfit": 0,
    "pips": 0,
    "balance": null,
    "equity": 10078.450000000003
  },
  {
    "serial": 135,
    "orderId": null,
    "positionId": 9,
    "event": "Position Modified (S/L)",
    "time": 1783038222270,
    "volume": 3,
    "quantity": 0.03,
    "type": "Buy",
    "entryPrice": 4119.38,
    "tp": 4151.93,
    "sl": 4136.47,
    "closePrice": null,
    "grossProfit": 0,
    "pips": 0,
    "balance": null,
    "equity": 10078.570000000002
  },
  {
    "serial": 136,
    "orderId": null,
    "positionId": 9,
    "event": "Position Modified (S/L)",
    "time": 1783038222631,
    "volume": 3,
    "quantity": 0.03,
    "type": "Buy",
    "entryPrice": 4119.38,
    "tp": 4151.93,
    "sl": 4136.5,
    "closePrice": null,
    "grossProfit": 0,
    "pips": 0,
    "balance": null,
    "equity": 10078.630000000003
  },
  {
    "serial": 137,
    "orderId": null,
    "positionId": 9,
    "event": "Position Modified (S/L)",
    "time": 1783038224834,
    "volume": 3,
    "quantity": 0.03,
    "type": "Buy",
    "entryPrice": 4119.38,
    "tp": 4151.93,
    "sl": 4136.8,
    "closePrice": null,
    "grossProfit": 0,
    "pips": 0,
    "balance": null,
    "equity": 10079.530000000002
  },
  {
    "serial": 138,
    "orderId": null,
    "positionId": 9,
    "event": "Position Modified (S/L)",
    "time": 1783038225206,
    "volume": 3,
    "quantity": 0.03,
    "type": "Buy",
    "entryPrice": 4119.38,
    "tp": 4151.93,
    "sl": 4136.92,
    "closePrice": null,
    "grossProfit": 0,
    "pips": 0,
    "balance": null,
    "equity": 10079.890000000001
  },
  {
    "serial": 139,
    "orderId": null,
    "positionId": 9,
    "event": "Position Modified (S/L)",
    "time": 1783038225919,
    "volume": 3,
    "quantity": 0.03,
    "type": "Buy",
    "entryPrice": 4119.38,
    "tp": 4151.93,
    "sl": 4136.93,
    "closePrice": null,
    "grossProfit": 0,
    "pips": 0,
    "balance": null,
    "equity": 10079.950000000003
  },
  {
    "serial": 140,
    "orderId": null,
    "positionId": 9,
    "event": "Position Modified (S/L)",
    "time": 1783038229166,
    "volume": 3,
    "quantity": 0.03,
    "type": "Buy",
    "entryPrice": 4119.38,
    "tp": 4151.93,
    "sl": 4137.01,
    "closePrice": null,
    "grossProfit": 0,
    "pips": 0,
    "balance": null,
    "equity": 10080.160000000002
  },
  {
    "serial": 141,
    "orderId": null,
    "positionId": 9,
    "event": "Position Modified (S/L)",
    "time": 1783038229518,
    "volume": 3,
    "quantity": 0.03,
    "type": "Buy",
    "entryPrice": 4119.38,
    "tp": 4151.93,
    "sl": 4137.04,
    "closePrice": null,
    "grossProfit": 0,
    "pips": 0,
    "balance": null,
    "equity": 10080.250000000002
  },
  {
    "serial": 142,
    "orderId": null,
    "positionId": 9,
    "event": "Position Modified (S/L)",
    "time": 1783038230241,
    "volume": 3,
    "quantity": 0.03,
    "type": "Buy",
    "entryPrice": 4119.38,
    "tp": 4151.93,
    "sl": 4137.09,
    "closePrice": null,
    "grossProfit": 0,
    "pips": 0,
    "balance": null,
    "equity": 10080.400000000001
  },
  {
    "serial": 143,
    "orderId": null,
    "positionId": 9,
    "event": "Position Modified (S/L)",
    "time": 1783038230626,
    "volume": 3,
    "quantity": 0.03,
    "type": "Buy",
    "entryPrice": 4119.38,
    "tp": 4151.93,
    "sl": 4137.34,
    "closePrice": null,
    "grossProfit": 0,
    "pips": 0,
    "balance": null,
    "equity": 10081.150000000001
  },
  {
    "serial": 144,
    "orderId": null,
    "positionId": 9,
    "event": "Position Modified (S/L)",
    "time": 1783038235486,
    "volume": 3,
    "quantity": 0.03,
    "type": "Buy",
    "entryPrice": 4119.38,
    "tp": 4151.93,
    "sl": 4137.47,
    "closePrice": null,
    "grossProfit": 0,
    "pips": 0,
    "balance": null,
    "equity": 10081.540000000003
  },
  {
    "serial": 145,
    "orderId": null,
    "positionId": 9,
    "event": "Position Modified (S/L)",
    "time": 1783038247889,
    "volume": 3,
    "quantity": 0.03,
    "type": "Buy",
    "entryPrice": 4119.38,
    "tp": 4151.93,
    "sl": 4137.55,
    "closePrice": null,
    "grossProfit": 0,
    "pips": 0,
    "balance": null,
    "equity": 10081.780000000002
  },
  {
    "serial": 146,
    "orderId": null,
    "positionId": 9,
    "event": "Stop Loss Hit",
    "time": 1783038338576,
    "volume": 3,
    "quantity": 0.03,
    "type": "Buy",
    "entryPrice": 4119.38,
    "tp": 4151.93,
    "sl": 4137.55,
    "closePrice": 4137.51,
    "grossProfit": 54.39,
    "pips": 1812.9999999999998,
    "balance": 10071.760000000002,
    "equity": 10070.170000000002
  },
  {
    "serial": 147,
    "orderId": null,
    "positionId": 10,
    "event": "Create Position",
    "time": 1783327500389,
    "volume": 7,
    "quantity": 0.07,
    "type": "Buy",
    "entryPrice": 4149.26,
    "tp": 4162.530000000001,
    "sl": 4142.27,
    "closePrice": null,
    "grossProfit": 0,
    "pips": 0,
    "balance": null,
    "equity": 10071.760000000002
  },
  {
    "serial": 148,
    "orderId": null,
    "positionId": 10,
    "event": "Stop Loss Hit",
    "time": 1783330122792,
    "volume": 7,
    "quantity": 0.07,
    "type": "Buy",
    "entryPrice": 4149.26,
    "tp": 4162.530000000001,
    "sl": 4142.27,
    "closePrice": 4142.17,
    "grossProfit": -49.63,
    "pips": -709,
    "balance": 10020.450000000003,
    "equity": 10020.450000000003
  },
  {
    "serial": 149,
    "orderId": null,
    "positionId": 11,
    "event": "Create Position",
    "time": 1783384200167,
    "volume": 5,
    "quantity": 0.05,
    "type": "Buy",
    "entryPrice": 4159.92,
    "tp": 4177.64,
    "sl": 4151,
    "closePrice": null,
    "grossProfit": 0,
    "pips": 0,
    "balance": null,
    "equity": 10020.450000000003
  },
  {
    "serial": 150,
    "orderId": null,
    "positionId": 11,
    "event": "Stop Loss Hit",
    "time": 1783384691643,
    "volume": 5,
    "quantity": 0.05,
    "type": "Buy",
    "entryPrice": 4159.92,
    "tp": 4177.64,
    "sl": 4151,
    "closePrice": 4150.93,
    "grossProfit": -44.95,
    "pips": -899,
    "balance": 9974.300000000003,
    "equity": 9974.300000000003
  },
  {
    "serial": 151,
    "orderId": null,
    "positionId": 12,
    "event": "Create Position",
    "time": 1783475100085,
    "volume": 5,
    "quantity": 0.05,
    "type": "Buy",
    "entryPrice": 4103.36,
    "tp": 4123,
    "sl": 4093.5599999999995,
    "closePrice": null,
    "grossProfit": 0,
    "pips": 0,
    "balance": null,
    "equity": 9974.300000000003
  },
  {
    "serial": 152,
    "orderId": null,
    "positionId": 12,
    "event": "Position Modified (S/L)",
    "time": 1783476444885,
    "volume": 5,
    "quantity": 0.05,
    "type": "Buy",
    "entryPrice": 4103.36,
    "tp": 4123,
    "sl": 4112.25,
    "closePrice": null,
    "grossProfit": 0,
    "pips": 0,
    "balance": null,
    "equity": 10027.350000000002
  },
  {
    "serial": 153,
    "orderId": null,
    "positionId": 12,
    "event": "Position Modified (S/L)",
    "time": 1783476445259,
    "volume": 5,
    "quantity": 0.05,
    "type": "Buy",
    "entryPrice": 4103.36,
    "tp": 4123,
    "sl": 4112.27,
    "closePrice": null,
    "grossProfit": 0,
    "pips": 0,
    "balance": null,
    "equity": 10027.450000000003
  },
  {
    "serial": 154,
    "orderId": null,
    "positionId": 12,
    "event": "Position Modified (S/L)",
    "time": 1783476445614,
    "volume": 5,
    "quantity": 0.05,
    "type": "Buy",
    "entryPrice": 4103.36,
    "tp": 4123,
    "sl": 4112.32,
    "closePrice": null,
    "grossProfit": 0,
    "pips": 0,
    "balance": null,
    "equity": 10027.700000000003
  },
  {
    "serial": 155,
    "orderId": null,
    "positionId": 12,
    "event": "Position Modified (S/L)",
    "time": 1783476445975,
    "volume": 5,
    "quantity": 0.05,
    "type": "Buy",
    "entryPrice": 4103.36,
    "tp": 4123,
    "sl": 4112.38,
    "closePrice": null,
    "grossProfit": 0,
    "pips": 0,
    "balance": null,
    "equity": 10028.000000000004
  },
  {
    "serial": 156,
    "orderId": null,
    "positionId": 12,
    "event": "Position Modified (S/L)",
    "time": 1783476460244,
    "volume": 5,
    "quantity": 0.05,
    "type": "Buy",
    "entryPrice": 4103.36,
    "tp": 4123,
    "sl": 4112.49,
    "closePrice": null,
    "grossProfit": 0,
    "pips": 0,
    "balance": null,
    "equity": 10028.550000000003
  },
  {
    "serial": 157,
    "orderId": null,
    "positionId": 12,
    "event": "Position Modified (S/L)",
    "time": 1783476460605,
    "volume": 5,
    "quantity": 0.05,
    "type": "Buy",
    "entryPrice": 4103.36,
    "tp": 4123,
    "sl": 4112.58,
    "closePrice": null,
    "grossProfit": 0,
    "pips": 0,
    "balance": null,
    "equity": 10029.000000000004
  },
  {
    "serial": 158,
    "orderId": null,
    "positionId": 12,
    "event": "Position Modified (S/L)",
    "time": 1783476460976,
    "volume": 5,
    "quantity": 0.05,
    "type": "Buy",
    "entryPrice": 4103.36,
    "tp": 4123,
    "sl": 4112.6,
    "closePrice": null,
    "grossProfit": 0,
    "pips": 0,
    "balance": null,
    "equity": 10029.150000000003
  },
  {
    "serial": 159,
    "orderId": null,
    "positionId": 12,
    "event": "Position Modified (S/L)",
    "time": 1783476461341,
    "volume": 5,
    "quantity": 0.05,
    "type": "Buy",
    "entryPrice": 4103.36,
    "tp": 4123,
    "sl": 4112.66,
    "closePrice": null,
    "grossProfit": 0,
    "pips": 0,
    "balance": null,
    "equity": 10029.400000000003
  },
  {
    "serial": 160,
    "orderId": null,
    "positionId": 12,
    "event": "Position Modified (S/L)",
    "time": 1783476462089,
    "volume": 5,
    "quantity": 0.05,
    "type": "Buy",
    "entryPrice": 4103.36,
    "tp": 4123,
    "sl": 4112.72,
    "closePrice": null,
    "grossProfit": 0,
    "pips": 0,
    "balance": null,
    "equity": 10029.750000000004
  },
  {
    "serial": 161,
    "orderId": null,
    "positionId": 12,
    "event": "Position Modified (S/L)",
    "time": 1783476464651,
    "volume": 5,
    "quantity": 0.05,
    "type": "Buy",
    "entryPrice": 4103.36,
    "tp": 4123,
    "sl": 4112.75,
    "closePrice": null,
    "grossProfit": 0,
    "pips": 0,
    "balance": null,
    "equity": 10029.850000000002
  },
  {
    "serial": 162,
    "orderId": null,
    "positionId": 12,
    "event": "Position Modified (S/L)",
    "time": 1783476465383,
    "volume": 5,
    "quantity": 0.05,
    "type": "Buy",
    "entryPrice": 4103.36,
    "tp": 4123,
    "sl": 4112.76,
    "closePrice": null,
    "grossProfit": 0,
    "pips": 0,
    "balance": null,
    "equity": 10029.900000000003
  },
  {
    "serial": 163,
    "orderId": null,
    "positionId": 12,
    "event": "Position Modified (S/L)",
    "time": 1783476465739,
    "volume": 5,
    "quantity": 0.05,
    "type": "Buy",
    "entryPrice": 4103.36,
    "tp": 4123,
    "sl": 4113.26,
    "closePrice": null,
    "grossProfit": 0,
    "pips": 0,
    "balance": null,
    "equity": 10032.400000000003
  },
  {
    "serial": 164,
    "orderId": null,
    "positionId": 12,
    "event": "Position Modified (S/L)",
    "time": 1783476466099,
    "volume": 5,
    "quantity": 0.05,
    "type": "Buy",
    "entryPrice": 4103.36,
    "tp": 4123,
    "sl": 4113.27,
    "closePrice": null,
    "grossProfit": 0,
    "pips": 0,
    "balance": null,
    "equity": 10032.450000000003
  },
  {
    "serial": 165,
    "orderId": null,
    "positionId": 12,
    "event": "Position Modified (S/L)",
    "time": 1783476466857,
    "volume": 5,
    "quantity": 0.05,
    "type": "Buy",
    "entryPrice": 4103.36,
    "tp": 4123,
    "sl": 4113.3,
    "closePrice": null,
    "grossProfit": 0,
    "pips": 0,
    "balance": null,
    "equity": 10032.600000000002
  },
  {
    "serial": 166,
    "orderId": null,
    "positionId": 12,
    "event": "Position Modified (S/L)",
    "time": 1783476467974,
    "volume": 5,
    "quantity": 0.05,
    "type": "Buy",
    "entryPrice": 4103.36,
    "tp": 4123,
    "sl": 4113.35,
    "closePrice": null,
    "grossProfit": 0,
    "pips": 0,
    "balance": null,
    "equity": 10032.900000000003
  },
  {
    "serial": 167,
    "orderId": null,
    "positionId": 12,
    "event": "Position Modified (S/L)",
    "time": 1783476484219,
    "volume": 5,
    "quantity": 0.05,
    "type": "Buy",
    "entryPrice": 4103.36,
    "tp": 4123,
    "sl": 4113.46,
    "closePrice": null,
    "grossProfit": 0,
    "pips": 0,
    "balance": null,
    "equity": 10033.400000000003
  },
  {
    "serial": 168,
    "orderId": null,
    "positionId": 12,
    "event": "Position Modified (S/L)",
    "time": 1783476486039,
    "volume": 5,
    "quantity": 0.05,
    "type": "Buy",
    "entryPrice": 4103.36,
    "tp": 4123,
    "sl": 4113.62,
    "closePrice": null,
    "grossProfit": 0,
    "pips": 0,
    "balance": null,
    "equity": 10034.200000000003
  },
  {
    "serial": 169,
    "orderId": null,
    "positionId": 12,
    "event": "Position Modified (S/L)",
    "time": 1783476486400,
    "volume": 5,
    "quantity": 0.05,
    "type": "Buy",
    "entryPrice": 4103.36,
    "tp": 4123,
    "sl": 4113.72,
    "closePrice": null,
    "grossProfit": 0,
    "pips": 0,
    "balance": null,
    "equity": 10034.700000000003
  },
  {
    "serial": 170,
    "orderId": null,
    "positionId": 12,
    "event": "Position Modified (S/L)",
    "time": 1783476486758,
    "volume": 5,
    "quantity": 0.05,
    "type": "Buy",
    "entryPrice": 4103.36,
    "tp": 4123,
    "sl": 4114.89,
    "closePrice": null,
    "grossProfit": 0,
    "pips": 0,
    "balance": null,
    "equity": 10040.600000000002
  },
  {
    "serial": 171,
    "orderId": null,
    "positionId": 12,
    "event": "Position Modified (S/L)",
    "time": 1783476487111,
    "volume": 5,
    "quantity": 0.05,
    "type": "Buy",
    "entryPrice": 4103.36,
    "tp": 4123,
    "sl": 4115.06,
    "closePrice": null,
    "grossProfit": 0,
    "pips": 0,
    "balance": null,
    "equity": 10041.400000000003
  },
  {
    "serial": 172,
    "orderId": null,
    "positionId": 12,
    "event": "Position Modified (S/L)",
    "time": 1783476487485,
    "volume": 5,
    "quantity": 0.05,
    "type": "Buy",
    "entryPrice": 4103.36,
    "tp": 4123,
    "sl": 4115.43,
    "closePrice": null,
    "grossProfit": 0,
    "pips": 0,
    "balance": null,
    "equity": 10043.300000000003
  },
  {
    "serial": 173,
    "orderId": null,
    "positionId": 12,
    "event": "Stop Loss Hit",
    "time": 1783476542815,
    "volume": 5,
    "quantity": 0.05,
    "type": "Buy",
    "entryPrice": 4103.36,
    "tp": 4123,
    "sl": 4115.43,
    "closePrice": 4115.41,
    "grossProfit": 60.25,
    "pips": 1205,
    "balance": 10033.350000000002,
    "equity": 10033.350000000002
  },
  {
    "serial": 174,
    "orderId": null,
    "positionId": 13,
    "event": "Create Position",
    "time": 1783598400124,
    "volume": 9,
    "quantity": 0.09,
    "type": "Sell",
    "entryPrice": 4108.84,
    "tp": 4097.87,
    "sl": 4114.16,
    "closePrice": null,
    "grossProfit": 0,
    "pips": 0,
    "balance": null,
    "equity": 10033.350000000002
  },
  {
    "serial": 175,
    "orderId": null,
    "positionId": 13,
    "event": "Stop Loss Hit",
    "time": 1783598919288,
    "volume": 9,
    "quantity": 0.09,
    "type": "Sell",
    "entryPrice": 4108.84,
    "tp": 4097.87,
    "sl": 4114.16,
    "closePrice": 4114.65,
    "grossProfit": -52.29,
    "pips": -581,
    "balance": 9978.900000000001,
    "equity": 9978.900000000001
  },
  {
    "serial": 176,
    "orderId": null,
    "positionId": 14,
    "event": "Create Position",
    "time": 1783653300131,
    "volume": 4,
    "quantity": 0.04,
    "type": "Sell",
    "entryPrice": 4126.67,
    "tp": 4105.27,
    "sl": 4137.28,
    "closePrice": null,
    "grossProfit": 0,
    "pips": 0,
    "balance": null,
    "equity": 9978.900000000001
  },
  {
    "serial": 177,
    "orderId": null,
    "positionId": 14,
    "event": "Position Modified (S/L)",
    "time": 1783657333360,
    "volume": 4,
    "quantity": 0.04,
    "type": "Sell",
    "entryPrice": 4126.67,
    "tp": 4105.27,
    "sl": 4116.88,
    "closePrice": null,
    "grossProfit": 0,
    "pips": 0,
    "balance": null,
    "equity": 10025.580000000002
  },
  {
    "serial": 178,
    "orderId": null,
    "positionId": 14,
    "event": "Position Modified (S/L)",
    "time": 1783657333725,
    "volume": 4,
    "quantity": 0.04,
    "type": "Sell",
    "entryPrice": 4126.67,
    "tp": 4105.27,
    "sl": 4116.57,
    "closePrice": null,
    "grossProfit": 0,
    "pips": 0,
    "balance": null,
    "equity": 10026.820000000002
  },
  {
    "serial": 179,
    "orderId": null,
    "positionId": 14,
    "event": "Position Modified (S/L)",
    "time": 1783657337011,
    "volume": 4,
    "quantity": 0.04,
    "type": "Sell",
    "entryPrice": 4126.67,
    "tp": 4105.27,
    "sl": 4116.47,
    "closePrice": null,
    "grossProfit": 0,
    "pips": 0,
    "balance": null,
    "equity": 10027.220000000001
  },
  {
    "serial": 180,
    "orderId": null,
    "positionId": 14,
    "event": "Position Modified (S/L)",
    "time": 1783657339581,
    "volume": 4,
    "quantity": 0.04,
    "type": "Sell",
    "entryPrice": 4126.67,
    "tp": 4105.27,
    "sl": 4116.43,
    "closePrice": null,
    "grossProfit": 0,
    "pips": 0,
    "balance": null,
    "equity": 10027.340000000002
  },
  {
    "serial": 181,
    "orderId": null,
    "positionId": 14,
    "event": "Position Modified (S/L)",
    "time": 1783657341000,
    "volume": 4,
    "quantity": 0.04,
    "type": "Sell",
    "entryPrice": 4126.67,
    "tp": 4105.27,
    "sl": 4116.37,
    "closePrice": null,
    "grossProfit": 0,
    "pips": 0,
    "balance": null,
    "equity": 10027.62
  },
  {
    "serial": 182,
    "orderId": null,
    "positionId": 14,
    "event": "Position Modified (S/L)",
    "time": 1783657344261,
    "volume": 4,
    "quantity": 0.04,
    "type": "Sell",
    "entryPrice": 4126.67,
    "tp": 4105.27,
    "sl": 4116.26,
    "closePrice": null,
    "grossProfit": 0,
    "pips": 0,
    "balance": null,
    "equity": 10028.060000000001
  },
  {
    "serial": 183,
    "orderId": null,
    "positionId": 14,
    "event": "Position Modified (S/L)",
    "time": 1783657344974,
    "volume": 4,
    "quantity": 0.04,
    "type": "Sell",
    "entryPrice": 4126.67,
    "tp": 4105.27,
    "sl": 4116.22,
    "closePrice": null,
    "grossProfit": 0,
    "pips": 0,
    "balance": null,
    "equity": 10028.220000000001
  },
  {
    "serial": 184,
    "orderId": null,
    "positionId": 14,
    "event": "Position Modified (S/L)",
    "time": 1783657345337,
    "volume": 4,
    "quantity": 0.04,
    "type": "Sell",
    "entryPrice": 4126.67,
    "tp": 4105.27,
    "sl": 4116.2,
    "closePrice": null,
    "grossProfit": 0,
    "pips": 0,
    "balance": null,
    "equity": 10028.300000000001
  },
  {
    "serial": 185,
    "orderId": null,
    "positionId": 14,
    "event": "Position Modified (S/L)",
    "time": 1783657353867,
    "volume": 4,
    "quantity": 0.04,
    "type": "Sell",
    "entryPrice": 4126.67,
    "tp": 4105.27,
    "sl": 4116.03,
    "closePrice": null,
    "grossProfit": 0,
    "pips": 0,
    "balance": null,
    "equity": 10028.980000000001
  },
  {
    "serial": 186,
    "orderId": null,
    "positionId": 14,
    "event": "Position Modified (S/L)",
    "time": 1783657361185,
    "volume": 4,
    "quantity": 0.04,
    "type": "Sell",
    "entryPrice": 4126.67,
    "tp": 4105.27,
    "sl": 4116.01,
    "closePrice": null,
    "grossProfit": 0,
    "pips": 0,
    "balance": null,
    "equity": 10029.060000000001
  },
  {
    "serial": 187,
    "orderId": null,
    "positionId": 14,
    "event": "Position Modified (S/L)",
    "time": 1783657361548,
    "volume": 4,
    "quantity": 0.04,
    "type": "Sell",
    "entryPrice": 4126.67,
    "tp": 4105.27,
    "sl": 4115.85,
    "closePrice": null,
    "grossProfit": 0,
    "pips": 0,
    "balance": null,
    "equity": 10029.660000000002
  },
  {
    "serial": 188,
    "orderId": null,
    "positionId": 14,
    "event": "Position Modified (S/L)",
    "time": 1783657361902,
    "volume": 4,
    "quantity": 0.04,
    "type": "Sell",
    "entryPrice": 4126.67,
    "tp": 4105.27,
    "sl": 4115.64,
    "closePrice": null,
    "grossProfit": 0,
    "pips": 0,
    "balance": null,
    "equity": 10030.500000000002
  },
  {
    "serial": 189,
    "orderId": null,
    "positionId": 14,
    "event": "Position Modified (S/L)",
    "time": 1783657362271,
    "volume": 4,
    "quantity": 0.04,
    "type": "Sell",
    "entryPrice": 4126.67,
    "tp": 4105.27,
    "sl": 4115.26,
    "closePrice": null,
    "grossProfit": 0,
    "pips": 0,
    "balance": null,
    "equity": 10032.060000000001
  },
  {
    "serial": 190,
    "orderId": null,
    "positionId": 14,
    "event": "Position Modified (S/L)",
    "time": 1783657363718,
    "volume": 4,
    "quantity": 0.04,
    "type": "Sell",
    "entryPrice": 4126.67,
    "tp": 4105.27,
    "sl": 4115.03,
    "closePrice": null,
    "grossProfit": 0,
    "pips": 0,
    "balance": null,
    "equity": 10032.980000000001
  },
  {
    "serial": 191,
    "orderId": null,
    "positionId": 14,
    "event": "Position Modified (S/L)",
    "time": 1783657383906,
    "volume": 4,
    "quantity": 0.04,
    "type": "Sell",
    "entryPrice": 4126.67,
    "tp": 4105.27,
    "sl": 4114.96,
    "closePrice": null,
    "grossProfit": 0,
    "pips": 0,
    "balance": null,
    "equity": 10033.260000000002
  },
  {
    "serial": 192,
    "orderId": null,
    "positionId": 14,
    "event": "Position Modified (S/L)",
    "time": 1783657405274,
    "volume": 4,
    "quantity": 0.04,
    "type": "Sell",
    "entryPrice": 4126.67,
    "tp": 4105.27,
    "sl": 4114.55,
    "closePrice": null,
    "grossProfit": 0,
    "pips": 0,
    "balance": null,
    "equity": 10034.900000000001
  },
  {
    "serial": 193,
    "orderId": null,
    "positionId": 14,
    "event": "Position Modified (S/L)",
    "time": 1783657429951,
    "volume": 4,
    "quantity": 0.04,
    "type": "Sell",
    "entryPrice": 4126.67,
    "tp": 4105.27,
    "sl": 4114.54,
    "closePrice": null,
    "grossProfit": 0,
    "pips": 0,
    "balance": null,
    "equity": 10034.940000000002
  },
  {
    "serial": 194,
    "orderId": null,
    "positionId": 14,
    "event": "Position Modified (S/L)",
    "time": 1783657430666,
    "volume": 4,
    "quantity": 0.04,
    "type": "Sell",
    "entryPrice": 4126.67,
    "tp": 4105.27,
    "sl": 4114.47,
    "closePrice": null,
    "grossProfit": 0,
    "pips": 0,
    "balance": null,
    "equity": 10035.180000000002
  },
  {
    "serial": 195,
    "orderId": null,
    "positionId": 14,
    "event": "Position Modified (S/L)",
    "time": 1783657431742,
    "volume": 4,
    "quantity": 0.04,
    "type": "Sell",
    "entryPrice": 4126.67,
    "tp": 4105.27,
    "sl": 4114.46,
    "closePrice": null,
    "grossProfit": 0,
    "pips": 0,
    "balance": null,
    "equity": 10035.260000000002
  },
  {
    "serial": 196,
    "orderId": null,
    "positionId": 14,
    "event": "Position Modified (S/L)",
    "time": 1783657432103,
    "volume": 4,
    "quantity": 0.04,
    "type": "Sell",
    "entryPrice": 4126.67,
    "tp": 4105.27,
    "sl": 4114.43,
    "closePrice": null,
    "grossProfit": 0,
    "pips": 0,
    "balance": null,
    "equity": 10035.380000000001
  },
  {
    "serial": 197,
    "orderId": null,
    "positionId": 14,
    "event": "Position Modified (S/L)",
    "time": 1783657433533,
    "volume": 4,
    "quantity": 0.04,
    "type": "Sell",
    "entryPrice": 4126.67,
    "tp": 4105.27,
    "sl": 4114.39,
    "closePrice": null,
    "grossProfit": 0,
    "pips": 0,
    "balance": null,
    "equity": 10035.500000000002
  },
  {
    "serial": 198,
    "orderId": null,
    "positionId": 14,
    "event": "Stop Loss Hit",
    "time": 1783657497749,
    "volume": 4,
    "quantity": 0.04,
    "type": "Sell",
    "entryPrice": 4126.67,
    "tp": 4105.27,
    "sl": 4114.39,
    "closePrice": 4114.44,
    "grossProfit": 48.92,
    "pips": 1223,
    "balance": 10026.86,
    "equity": 10026.86
  },
  {
    "serial": 199,
    "orderId": null,
    "positionId": 15,
    "event": "Create Position",
    "time": 1783683900138,
    "volume": 4,
    "quantity": 0.04,
    "type": "Buy",
    "entryPrice": 4106.75,
    "tp": 4131.43,
    "sl": 4094.47,
    "closePrice": null,
    "grossProfit": 0,
    "pips": 0,
    "balance": null,
    "equity": 10026.86
  },
  {
    "serial": 200,
    "orderId": null,
    "positionId": 15,
    "event": "Stop Loss Hit",
    "time": 1783690047064,
    "volume": 4,
    "quantity": 0.04,
    "type": "Buy",
    "entryPrice": 4106.75,
    "tp": 4131.43,
    "sl": 4094.47,
    "closePrice": 4094.31,
    "grossProfit": -49.76,
    "pips": -1244,
    "balance": 9976.140000000001,
    "equity": 9976.140000000001
  },
  {
    "serial": 201,
    "orderId": null,
    "positionId": 16,
    "event": "Create Position",
    "time": 1783693800170,
    "volume": 5,
    "quantity": 0.05,
    "type": "Sell",
    "entryPrice": 4105.64,
    "tp": 4087.09,
    "sl": 4114.71,
    "closePrice": null,
    "grossProfit": 0,
    "pips": 0,
    "balance": null,
    "equity": 9976.140000000001
  },
  {
    "serial": 202,
    "orderId": null,
    "positionId": 16,
    "event": "Position Modified (S/L)",
    "time": 1783693967021,
    "volume": 5,
    "quantity": 0.05,
    "type": "Sell",
    "entryPrice": 4105.64,
    "tp": 4087.09,
    "sl": 4096.53,
    "closePrice": null,
    "grossProfit": 0,
    "pips": 0,
    "balance": null,
    "equity": 10029.54
  },
  {
    "serial": 203,
    "orderId": null,
    "positionId": 16,
    "event": "Position Modified (S/L)",
    "time": 1783693967377,
    "volume": 5,
    "quantity": 0.05,
    "type": "Sell",
    "entryPrice": 4105.64,
    "tp": 4087.09,
    "sl": 4096.39,
    "closePrice": null,
    "grossProfit": 0,
    "pips": 0,
    "balance": null,
    "equity": 10030.240000000002
  },
  {
    "serial": 204,
    "orderId": null,
    "positionId": 16,
    "event": "Position Modified (S/L)",
    "time": 1783693967729,
    "volume": 5,
    "quantity": 0.05,
    "type": "Sell",
    "entryPrice": 4105.64,
    "tp": 4087.09,
    "sl": 4096.14,
    "closePrice": null,
    "grossProfit": 0,
    "pips": 0,
    "balance": null,
    "equity": 10031.44
  },
  {
    "serial": 205,
    "orderId": null,
    "positionId": 16,
    "event": "Stop Loss Hit",
    "time": 1783693968814,
    "volume": 5,
    "quantity": 0.05,
    "type": "Sell",
    "entryPrice": 4105.64,
    "tp": 4087.09,
    "sl": 4096.14,
    "closePrice": 4096.33,
    "grossProfit": 46.55,
    "pips": 931,
    "balance": 10021.490000000002,
    "equity": 10021.490000000002
  },
  {
    "serial": 206,
    "orderId": null,
    "positionId": 17,
    "event": "Create Position",
    "time": 1783694700199,
    "volume": 3,
    "quantity": 0.03,
    "type": "Sell",
    "entryPrice": 4099.07,
    "tp": 4072.62,
    "sl": 4112.75,
    "closePrice": null,
    "grossProfit": 0,
    "pips": 0,
    "balance": null,
    "equity": 10021.490000000002
  },
  {
    "serial": 207,
    "orderId": null,
    "positionId": 17,
    "event": "Stop Loss Hit",
    "time": 1783699141263,
    "volume": 3,
    "quantity": 0.03,
    "type": "Sell",
    "entryPrice": 4099.07,
    "tp": 4072.62,
    "sl": 4112.75,
    "closePrice": 4113.48,
    "grossProfit": -43.23,
    "pips": -1441,
    "balance": 9977.54,
    "equity": 9977.54
  },
  {
    "serial": 208,
    "orderId": null,
    "positionId": 18,
    "event": "Create Position",
    "time": 1783941300332,
    "volume": 2,
    "quantity": 0.02,
    "type": "Sell",
    "entryPrice": 4064.13,
    "tp": 4030.58,
    "sl": 4080.88,
    "closePrice": null,
    "grossProfit": 0,
    "pips": 0,
    "balance": null,
    "equity": 9977.54
  },
  {
    "serial": 209,
    "orderId": null,
    "positionId": 18,
    "event": "Position Modified (S/L)",
    "time": 1783950710169,
    "volume": 2,
    "quantity": 0.02,
    "type": "Sell",
    "entryPrice": 4064.13,
    "tp": 4030.58,
    "sl": 4048.37,
    "closePrice": null,
    "grossProfit": 0,
    "pips": 0,
    "balance": null,
    "equity": 10015.28
  },
  {
    "serial": 210,
    "orderId": null,
    "positionId": 18,
    "event": "Position Modified (S/L)",
    "time": 1783950710532,
    "volume": 2,
    "quantity": 0.02,
    "type": "Sell",
    "entryPrice": 4064.13,
    "tp": 4030.58,
    "sl": 4048.25,
    "closePrice": null,
    "grossProfit": 0,
    "pips": 0,
    "balance": null,
    "equity": 10015.52
  },
  {
    "serial": 211,
    "orderId": null,
    "positionId": 18,
    "event": "Position Modified (S/L)",
    "time": 1783950710885,
    "volume": 2,
    "quantity": 0.02,
    "type": "Sell",
    "entryPrice": 4064.13,
    "tp": 4030.58,
    "sl": 4046.6,
    "closePrice": null,
    "grossProfit": 0,
    "pips": 0,
    "balance": null,
    "equity": 10018.820000000002
  },
  {
    "serial": 212,
    "orderId": null,
    "positionId": 18,
    "event": "Position Modified (S/L)",
    "time": 1783950711596,
    "volume": 2,
    "quantity": 0.02,
    "type": "Sell",
    "entryPrice": 4064.13,
    "tp": 4030.58,
    "sl": 4046.56,
    "closePrice": null,
    "grossProfit": 0,
    "pips": 0,
    "balance": null,
    "equity": 10018.900000000001
  },
  {
    "serial": 213,
    "orderId": null,
    "positionId": 18,
    "event": "Position Modified (S/L)",
    "time": 1783950716269,
    "volume": 2,
    "quantity": 0.02,
    "type": "Sell",
    "entryPrice": 4064.13,
    "tp": 4030.58,
    "sl": 4046.53,
    "closePrice": null,
    "grossProfit": 0,
    "pips": 0,
    "balance": null,
    "equity": 10018.960000000001
  },
  {
    "serial": 214,
    "orderId": null,
    "positionId": 18,
    "event": "Position Modified (S/L)",
    "time": 1783950716986,
    "volume": 2,
    "quantity": 0.02,
    "type": "Sell",
    "entryPrice": 4064.13,
    "tp": 4030.58,
    "sl": 4046.36,
    "closePrice": null,
    "grossProfit": 0,
    "pips": 0,
    "balance": null,
    "equity": 10019.300000000001
  },
  {
    "serial": 215,
    "orderId": null,
    "positionId": 18,
    "event": "Position Modified (S/L)",
    "time": 1783950717337,
    "volume": 2,
    "quantity": 0.02,
    "type": "Sell",
    "entryPrice": 4064.13,
    "tp": 4030.58,
    "sl": 4046.28,
    "closePrice": null,
    "grossProfit": 0,
    "pips": 0,
    "balance": null,
    "equity": 10019.460000000001
  },
  {
    "serial": 216,
    "orderId": null,
    "positionId": 18,
    "event": "Stop Loss Hit",
    "time": 1783950735172,
    "volume": 2,
    "quantity": 0.02,
    "type": "Sell",
    "entryPrice": 4064.13,
    "tp": 4030.58,
    "sl": 4046.28,
    "closePrice": 4046.3,
    "grossProfit": 35.66,
    "pips": 1782.9999999999998,
    "balance": 10012.720000000001,
    "equity": 10012.720000000001
  },
  {
    "serial": 217,
    "orderId": null,
    "positionId": 19,
    "event": "Create Position",
    "time": 1783987200299,
    "volume": 8,
    "quantity": 0.08,
    "type": "Sell",
    "entryPrice": 4001.6,
    "tp": 3988.77,
    "sl": 4007.31,
    "closePrice": null,
    "grossProfit": 0,
    "pips": 0,
    "balance": null,
    "equity": 10012.720000000001
  },
  {
    "serial": 218,
    "orderId": null,
    "positionId": 19,
    "event": "Position Modified (S/L)",
    "time": 1783987459740,
    "volume": 8,
    "quantity": 0.08,
    "type": "Sell",
    "entryPrice": 4001.6,
    "tp": 3988.77,
    "sl": 3996.2,
    "closePrice": null,
    "grossProfit": 0,
    "pips": 0,
    "balance": null,
    "equity": 10063.12
  },
  {
    "serial": 219,
    "orderId": null,
    "positionId": 19,
    "event": "Position Modified (S/L)",
    "time": 1783987460820,
    "volume": 8,
    "quantity": 0.08,
    "type": "Sell",
    "entryPrice": 4001.6,
    "tp": 3988.77,
    "sl": 3996.1,
    "closePrice": null,
    "grossProfit": 0,
    "pips": 0,
    "balance": null,
    "equity": 10063.920000000002
  },
  {
    "serial": 220,
    "orderId": null,
    "positionId": 19,
    "event": "Position Modified (S/L)",
    "time": 1783987461206,
    "volume": 8,
    "quantity": 0.08,
    "type": "Sell",
    "entryPrice": 4001.6,
    "tp": 3988.77,
    "sl": 3996.04,
    "closePrice": null,
    "grossProfit": 0,
    "pips": 0,
    "balance": null,
    "equity": 10064.400000000001
  },
  {
    "serial": 221,
    "orderId": null,
    "positionId": 19,
    "event": "Position Modified (S/L)",
    "time": 1783987461927,
    "volume": 8,
    "quantity": 0.08,
    "type": "Sell",
    "entryPrice": 4001.6,
    "tp": 3988.77,
    "sl": 3996.01,
    "closePrice": null,
    "grossProfit": 0,
    "pips": 0,
    "balance": null,
    "equity": 10064.640000000001
  },
  {
    "serial": 222,
    "orderId": null,
    "positionId": 19,
    "event": "Position Modified (S/L)",
    "time": 1783987463768,
    "volume": 8,
    "quantity": 0.08,
    "type": "Sell",
    "entryPrice": 4001.6,
    "tp": 3988.77,
    "sl": 3996,
    "closePrice": null,
    "grossProfit": 0,
    "pips": 0,
    "balance": null,
    "equity": 10064.720000000001
  },
  {
    "serial": 223,
    "orderId": null,
    "positionId": 19,
    "event": "Position Modified (S/L)",
    "time": 1783987466647,
    "volume": 8,
    "quantity": 0.08,
    "type": "Sell",
    "entryPrice": 4001.6,
    "tp": 3988.77,
    "sl": 3995.73,
    "closePrice": null,
    "grossProfit": 0,
    "pips": 0,
    "balance": null,
    "equity": 10066.880000000001
  },
  {
    "serial": 224,
    "orderId": null,
    "positionId": 19,
    "event": "Position Modified (S/L)",
    "time": 1783987467000,
    "volume": 8,
    "quantity": 0.08,
    "type": "Sell",
    "entryPrice": 4001.6,
    "tp": 3988.77,
    "sl": 3995.67,
    "closePrice": null,
    "grossProfit": 0,
    "pips": 0,
    "balance": null,
    "equity": 10067.36
  },
  {
    "serial": 225,
    "orderId": null,
    "positionId": 19,
    "event": "Position Modified (S/L)",
    "time": 1783987469911,
    "volume": 8,
    "quantity": 0.08,
    "type": "Sell",
    "entryPrice": 4001.6,
    "tp": 3988.77,
    "sl": 3995.25,
    "closePrice": null,
    "grossProfit": 0,
    "pips": 0,
    "balance": null,
    "equity": 10070.720000000001
  },
  {
    "serial": 226,
    "orderId": null,
    "positionId": 19,
    "event": "Position Modified (S/L)",
    "time": 1783987470274,
    "volume": 8,
    "quantity": 0.08,
    "type": "Sell",
    "entryPrice": 4001.6,
    "tp": 3988.77,
    "sl": 3995.24,
    "closePrice": null,
    "grossProfit": 0,
    "pips": 0,
    "balance": null,
    "equity": 10070.800000000001
  },
  {
    "serial": 227,
    "orderId": null,
    "positionId": 19,
    "event": "Position Modified (S/L)",
    "time": 1783987470987,
    "volume": 8,
    "quantity": 0.08,
    "type": "Sell",
    "entryPrice": 4001.6,
    "tp": 3988.77,
    "sl": 3995.05,
    "closePrice": null,
    "grossProfit": 0,
    "pips": 0,
    "balance": null,
    "equity": 10072.320000000002
  },
  {
    "serial": 228,
    "orderId": null,
    "positionId": 19,
    "event": "Position Modified (S/L)",
    "time": 1783987471342,
    "volume": 8,
    "quantity": 0.08,
    "type": "Sell",
    "entryPrice": 4001.6,
    "tp": 3988.77,
    "sl": 3994.89,
    "closePrice": null,
    "grossProfit": 0,
    "pips": 0,
    "balance": null,
    "equity": 10073.6
  },
  {
    "serial": 229,
    "orderId": null,
    "positionId": 19,
    "event": "Position Modified (S/L)",
    "time": 1783987471726,
    "volume": 8,
    "quantity": 0.08,
    "type": "Sell",
    "entryPrice": 4001.6,
    "tp": 3988.77,
    "sl": 3994.78,
    "closePrice": null,
    "grossProfit": 0,
    "pips": 0,
    "balance": null,
    "equity": 10074.480000000001
  },
  {
    "serial": 230,
    "orderId": null,
    "positionId": 19,
    "event": "Position Modified (S/L)",
    "time": 1783987472090,
    "volume": 8,
    "quantity": 0.08,
    "type": "Sell",
    "entryPrice": 4001.6,
    "tp": 3988.77,
    "sl": 3994.53,
    "closePrice": null,
    "grossProfit": 0,
    "pips": 0,
    "balance": null,
    "equity": 10076.480000000001
  },
  {
    "serial": 231,
    "orderId": null,
    "positionId": 19,
    "event": "Position Modified (S/L)",
    "time": 1783987472444,
    "volume": 8,
    "quantity": 0.08,
    "type": "Sell",
    "entryPrice": 4001.6,
    "tp": 3988.77,
    "sl": 3994.52,
    "closePrice": null,
    "grossProfit": 0,
    "pips": 0,
    "balance": null,
    "equity": 10076.560000000001
  },
  {
    "serial": 232,
    "orderId": null,
    "positionId": 19,
    "event": "Position Modified (S/L)",
    "time": 1783987481560,
    "volume": 8,
    "quantity": 0.08,
    "type": "Sell",
    "entryPrice": 4001.6,
    "tp": 3988.77,
    "sl": 3994.47,
    "closePrice": null,
    "grossProfit": 0,
    "pips": 0,
    "balance": null,
    "equity": 10076.960000000001
  },
  {
    "serial": 233,
    "orderId": null,
    "positionId": 19,
    "event": "Position Modified (S/L)",
    "time": 1783987481925,
    "volume": 8,
    "quantity": 0.08,
    "type": "Sell",
    "entryPrice": 4001.6,
    "tp": 3988.77,
    "sl": 3994.45,
    "closePrice": null,
    "grossProfit": 0,
    "pips": 0,
    "balance": null,
    "equity": 10077.12
  },
  {
    "serial": 234,
    "orderId": null,
    "positionId": 19,
    "event": "Position Modified (S/L)",
    "time": 1783987482276,
    "volume": 8,
    "quantity": 0.08,
    "type": "Sell",
    "entryPrice": 4001.6,
    "tp": 3988.77,
    "sl": 3994.41,
    "closePrice": null,
    "grossProfit": 0,
    "pips": 0,
    "balance": null,
    "equity": 10077.44
  },
  {
    "serial": 235,
    "orderId": null,
    "positionId": 19,
    "event": "Stop Loss Hit",
    "time": 1783987499645,
    "volume": 8,
    "quantity": 0.08,
    "type": "Sell",
    "entryPrice": 4001.6,
    "tp": 3988.77,
    "sl": 3994.41,
    "closePrice": 3994.49,
    "grossProfit": 56.88,
    "pips": 711,
    "balance": 10067.68,
    "equity": 10067.68
  },
  {
    "serial": 236,
    "orderId": null,
    "positionId": 20,
    "event": "Create Position",
    "time": 1783988100055,
    "volume": 4,
    "quantity": 0.04,
    "type": "Sell",
    "entryPrice": 3995.46,
    "tp": 3971.28,
    "sl": 4007.62,
    "closePrice": null,
    "grossProfit": 0,
    "pips": 0,
    "balance": null,
    "equity": 10067.68
  },
  {
    "serial": 237,
    "orderId": null,
    "positionId": 20,
    "event": "Stop Loss Hit",
    "time": 1783994294967,
    "volume": 4,
    "quantity": 0.04,
    "type": "Sell",
    "entryPrice": 3995.46,
    "tp": 3971.28,
    "sl": 4007.62,
    "closePrice": 4007.62,
    "grossProfit": -48.64,
    "pips": -1216,
    "balance": 10018.08,
    "equity": 10018.08
  },
  {
    "serial": 238,
    "orderId": null,
    "positionId": 21,
    "event": "Create Position",
    "time": 1784215800028,
    "volume": 1,
    "quantity": 0.01,
    "type": "Buy",
    "entryPrice": 4011.55,
    "tp": 4069.17,
    "sl": 3982.6200000000003,
    "closePrice": null,
    "grossProfit": 0,
    "pips": 0,
    "balance": null,
    "equity": 10018.08
  },
  {
    "serial": 239,
    "orderId": null,
    "positionId": 21,
    "event": "Stop Loss Hit",
    "time": 1784218821159,
    "volume": 1,
    "quantity": 0.01,
    "type": "Buy",
    "entryPrice": 4011.55,
    "tp": 4069.17,
    "sl": 3982.6200000000003,
    "closePrice": 3982.39,
    "grossProfit": -29.16,
    "pips": -2916,
    "balance": 9988.68,
    "equity": 9988.68
  },
  {
    "serial": 240,
    "orderId": null,
    "positionId": 22,
    "event": "Create Position",
    "time": 1784295900170,
    "volume": 2,
    "quantity": 0.02,
    "type": "Sell",
    "entryPrice": 3985.32,
    "tp": 3941.6600000000003,
    "sl": 4006.73,
    "closePrice": null,
    "grossProfit": 0,
    "pips": 0,
    "balance": null,
    "equity": 9988.68
  },
  {
    "serial": 241,
    "orderId": null,
    "positionId": 22,
    "event": "Stop Loss Hit",
    "time": 1784300665843,
    "volume": 2,
    "quantity": 0.02,
    "type": "Sell",
    "entryPrice": 3985.32,
    "tp": 3941.6600000000003,
    "sl": 4006.73,
    "closePrice": 4010.03,
    "grossProfit": -49.42,
    "pips": -2471,
    "balance": 9938.78,
    "equity": 9938.78
  },
  {
    "serial": 242,
    "orderId": null,
    "positionId": 23,
    "event": "Create Position",
    "time": 1784550600106,
    "volume": 5,
    "quantity": 0.05,
    "type": "Buy",
    "entryPrice": 4013.05,
    "tp": 4029.6400000000003,
    "sl": 4004.7000000000003,
    "closePrice": null,
    "grossProfit": 0,
    "pips": 0,
    "balance": null,
    "equity": 9938.78
  },
  {
    "serial": 243,
    "orderId": null,
    "positionId": 23,
    "event": "Stop Loss Hit",
    "time": 1784556035049,
    "volume": 5,
    "quantity": 0.05,
    "type": "Buy",
    "entryPrice": 4013.05,
    "tp": 4029.6400000000003,
    "sl": 4004.7000000000003,
    "closePrice": 4004.58,
    "grossProfit": -42.35,
    "pips": -847,
    "balance": 9895.230000000001,
    "equity": 9895.230000000001
  },
  {
    "serial": 244,
    "orderId": null,
    "positionId": 24,
    "event": "Create Position",
    "time": 1784565900307,
    "volume": 4,
    "quantity": 0.04,
    "type": "Buy",
    "entryPrice": 4009.67,
    "tp": 4030.4900000000002,
    "sl": 3999.21,
    "closePrice": null,
    "grossProfit": 0,
    "pips": 0,
    "balance": null,
    "equity": 9895.230000000001
  }
]